<?xml version="1.0" encoding="UTF-8" ?> 
<!DOCTYPE mapper PUBLIC "-//mybatis.org//DTD Mapper 3.0//EN" "http://mybatis.org/dtd/mybatis-3-mapper.dtd" >
<mapper namespace="CTSCARDS_MGT_ALERT" >
  <resultMap id="BaseResultMap" type="com.path.dbmaps.vo.CTSCARDS_MGT_ALERTVO" >
    <id column="APPLICATION_ID" property="APPLICATION_ID" />
    <id column="BRANCH_CODE" property="BRANCH_CODE" />
    <id column="COMP_CODE" property="COMP_CODE" />
    <result column="REFERENCE" property="REFERENCE" />
    <result column="CARD_TYPE" property="CARD_TYPE" />
    <result column="CIF" property="CIF" />
    <result column="CIF_STATUS" property="CIF_STATUS" />
    <result column="CIF_STATUS_REASON" property="CIF_STATUS_REASON" />
    <result column="CIF_STATUS_DATE" property="CIF_STATUS_DATE" />
    <result column="EFFECTIVE_DATE" property="EFFECTIVE_DATE" />
    <result column="EXPIRY_DATE" property="EXPIRY_DATE" />
    <result column="PREPARATION_DATE" property="PREPARATION_DATE" />
    <result column="STATUS" property="STATUS" />
    <result column="STATUS_REASON" property="STATUS_REASON" />
    <result column="DATE_CREATED" property="DATE_CREATED" />
    <result column="CREATED_BY" property="CREATED_BY" />
    <result column="DATE_APPROVED" property="DATE_APPROVED" />
    <result column="APPROVED_BY" property="APPROVED_BY" />
    <result column="DATE_ISSUED" property="DATE_ISSUED" />
    <result column="ISSUED_BY" property="ISSUED_BY" />
    <result column="DATE_ACTIVATED" property="DATE_ACTIVATED" />
    <result column="ACTIVATED_BY" property="ACTIVATED_BY" />
    <result column="DATE_BLOCKED" property="DATE_BLOCKED" />
    <result column="BLOCKED_BY" property="BLOCKED_BY" />
    <result column="DATE_MONITORED" property="DATE_MONITORED" />
    <result column="MONITORED_BY" property="MONITORED_BY" />
    <result column="DATE_DEACTIVATED" property="DATE_DEACTIVATED" />
    <result column="DEACTIVATED_BY" property="DEACTIVATED_BY" />
    <result column="DATE_CANCELLED" property="DATE_CANCELLED" />
    <result column="CANCELLED_BY" property="CANCELLED_BY" />
    <result column="DATE_REPLACED" property="DATE_REPLACED" />
    <result column="REPLACED_BY" property="REPLACED_BY" />
    <result column="LAST_STATUS" property="LAST_STATUS" />
    <result column="NEW_EFFECTIVE_DATE" property="NEW_EFFECTIVE_DATE" />
    <result column="NEW_EXPIRY_DATE" property="NEW_EXPIRY_DATE" />
    <result column="NEW_PREPARATION_DATE" property="NEW_PREPARATION_DATE" />
    <result column="DATE_MODIFIED" property="DATE_MODIFIED" />
    <result column="MODIFIED_BY" property="MODIFIED_BY" />
    <result column="DATE_DELETED" property="DATE_DELETED" />
    <result column="DELETED_BY" property="DELETED_BY" />
    <result column="DATE_RENEWED" property="DATE_RENEWED" />
    <result column="RENEWED_BY" property="RENEWED_BY" />
    <result column="PROCESSED" property="PROCESSED" />
    <result column="CARD_NO" property="CARD_NO" />
    <result column="PAYMENT_PERC" property="PAYMENT_PERC" />
    <result column="CARD_HOLDER_NAME" property="CARD_HOLDER_NAME" />
    <result column="REASON_DESC_ENG" property="REASON_DESC_ENG" />
    <result column="REASON_DESC_ARAB" property="REASON_DESC_ARAB" />
    <result column="PRIM_SUPP" property="PRIM_SUPP" />
    <result column="DATE_HEATED" property="DATE_HEATED" />
    <result column="HEATED_BY" property="HEATED_BY" />
    <result column="DEST_BRANCH" property="DEST_BRANCH" />
    <result column="DELIVERED_DATE" property="DELIVERED_DATE" />
    <result column="DELIVERED_LOC" property="DELIVERED_LOC" />
    <result column="TELLER_CODE" property="TELLER_CODE" />
    <result column="BATCH_NO" property="BATCH_NO" />
    <result column="USER_ID" property="USER_ID" />
    <result column="CTS_TRS_NO" property="CTS_TRS_NO" />
    <result column="CIVIL_ID" property="CIVIL_ID" />
    <result column="DEBIT_DAYS" property="DEBIT_DAYS" />
    <result column="FREE_CARD" property="FREE_CARD" />
    <result column="LIEN_INFORMATION" property="LIEN_INFORMATION" />
    <result column="SENT_KNET" property="SENT_KNET" />
    <result column="DESTROYED_BY" property="DESTROYED_BY" />
    <result column="DATE_DESTROYED" property="DATE_DESTROYED" />
    <result column="UNBLOCKED_BY" property="UNBLOCKED_BY" />
    <result column="DATE_UNBLOCKED" property="DATE_UNBLOCKED" />
    <result column="ID_TYPE" property="ID_TYPE" />
    <result column="NATION_CODE" property="NATION_CODE" />
    <result column="DATE_BIRTH" property="DATE_BIRTH" />
    <result column="TEL_NO" property="TEL_NO" />
    <result column="POBOX_AREA" property="POBOX_AREA" />
    <result column="PO_BOX" property="PO_BOX" />
    <result column="OCCUP_POSITION" property="OCCUP_POSITION" />
    <result column="DEPT" property="DEPT" />
    <result column="EMPL_DURATION" property="EMPL_DURATION" />
    <result column="EMP_TEL" property="EMP_TEL" />
    <result column="MONTHLY_SALARY" property="MONTHLY_SALARY" />
    <result column="EDUC_LEVEL" property="EDUC_LEVEL" />
    <result column="CREDIT_TYPE" property="CREDIT_TYPE" />
    <result column="BILLING_ACC" property="BILLING_ACC" />
    <result column="BANK_NAME" property="BANK_NAME" />
    <result column="ACCOUNT_NUMBER" property="ACCOUNT_NUMBER" />
    <result column="DIVISION" property="DIVISION" />
    <result column="CINET_CHECKED" property="CINET_CHECKED" />
    <result column="DATE_APPLIED" property="DATE_APPLIED" />
    <result column="APPLIED_BY" property="APPLIED_BY" />
    <result column="DATE_RECOMMEND" property="DATE_RECOMMEND" />
    <result column="RECOMMEND_BY" property="RECOMMEND_BY" />
    <result column="DATE_REJECTED" property="DATE_REJECTED" />
    <result column="REJECTED_BY" property="REJECTED_BY" />
    <result column="DATE_REVISED" property="DATE_REVISED" />
    <result column="REVISED_BY" property="REVISED_BY" />
    <result column="PAYMENT_DATE" property="PAYMENT_DATE" />
    <result column="PAYMENT_AMOUNT" property="PAYMENT_AMOUNT" />
    <result column="NEXT_BILLING_DATE" property="NEXT_BILLING_DATE" />
    <result column="EMAIL" property="EMAIL" />
    <result column="LIEN_ACC" property="LIEN_ACC" />
    <result column="OUTSTANDING_BALANCE" property="OUTSTANDING_BALANCE" />
    <result column="LAST_LIMIT_INCREASE" property="LAST_LIMIT_INCREASE" />
    <result column="MAILING_REGION" property="MAILING_REGION" />
    <result column="MAILING_ADDRESS1" property="MAILING_ADDRESS1" />
    <result column="MAILING_ADDRESS2" property="MAILING_ADDRESS2" />
    <result column="MAILING_ADDRESS3" property="MAILING_ADDRESS3" />
    <result column="MAILING_ADDRESS4" property="MAILING_ADDRESS4" />
    <result column="MAILING_CITY" property="MAILING_CITY" />
    <result column="MAILING_COUNTRY" property="MAILING_COUNTRY" />
    <result column="MAILING_POBOX_AREA" property="MAILING_POBOX_AREA" />
    <result column="MAILING_PO_BOX" property="MAILING_PO_BOX" />
    <result column="NO_OF_CARDS" property="NO_OF_CARDS" />
    <result column="IS_RENEWED" property="IS_RENEWED" />
    <result column="EMPLOYER_NAME" property="EMPLOYER_NAME" />
    <result column="REMAINING_AMOUNT" property="REMAINING_AMOUNT" />
    <result column="TOTAL_LIMIT" property="TOTAL_LIMIT" />
    <result column="SEXE" property="SEXE" />
    <result column="DATE_MODIFIED_1" property="DATE_MODIFIED_1" />
    <result column="MODIFIED_BY_1" property="MODIFIED_BY_1" />
    <result column="APP_REF" property="APP_REF" />
    <result column="LIMIT_BASED_ON" property="LIMIT_BASED_ON" />
    <result column="LIMIT_CHECK_PERIOD" property="LIMIT_CHECK_PERIOD" />
    <result column="POS_LIMIT_BASED_ON" property="POS_LIMIT_BASED_ON" />
    <result column="POS_LIMIT_CHECK_PERIOD" property="POS_LIMIT_CHECK_PERIOD" />
    <result column="POS_LIMIT_AMOUNT" property="POS_LIMIT_AMOUNT" />
    <result column="SENT_TO_PROV_BY" property="SENT_TO_PROV_BY" />
    <result column="DATE_SENT_TO_PROV" property="DATE_SENT_TO_PROV" />
    <result column="RECEIVED_FROM_PROV_BY" property="RECEIVED_FROM_PROV_BY" />
    <result column="DATE_RECEIVED_FROM_PROV" property="DATE_RECEIVED_FROM_PROV" />
    <result column="RECEIVED_BY_BRANCH_BY" property="RECEIVED_BY_BRANCH_BY" />
    <result column="DATE_RECEIVED_BY_BRANCH" property="DATE_RECEIVED_BY_BRANCH" />
    <result column="ISSUED_INIT" property="ISSUED_INIT" />
    <result column="DATE_ISSUED_INIT" property="DATE_ISSUED_INIT" />
    <result column="ACTIVATED_INIT" property="ACTIVATED_INIT" />
    <result column="DATE_ACTIVATED_INIT" property="DATE_ACTIVATED_INIT" />
    <result column="MONITORED_INIT" property="MONITORED_INIT" />
    <result column="DATE_MONITORED_INIT" property="DATE_MONITORED_INIT" />
    <result column="DEACTIVATED_INIT" property="DEACTIVATED_INIT" />
    <result column="DATE_DEACTIVATED_INIT" property="DATE_DEACTIVATED_INIT" />
    <result column="DESTROYED_INIT" property="DESTROYED_INIT" />
    <result column="DATE_DESTROYED_INIT" property="DATE_DESTROYED_INIT" />
    <result column="REPLACED_INIT" property="REPLACED_INIT" />
    <result column="DATE_REPLACED_INIT" property="DATE_REPLACED_INIT" />
    <result column="CANCELLED_INIT" property="CANCELLED_INIT" />
    <result column="DATE_CANCELLED_INIT" property="DATE_CANCELLED_INIT" />
    <result column="BLOCKED_INIT" property="BLOCKED_INIT" />
    <result column="DATE_BLOCKED_INIT" property="DATE_BLOCKED_INIT" />
    <result column="UNBLOCKED_INIT" property="UNBLOCKED_INIT" />
    <result column="DATE_UNBLOCKED_INIT" property="DATE_UNBLOCKED_INIT" />
    <result column="HEATED_INIT" property="HEATED_INIT" />
    <result column="DATE_HEATED_INIT" property="DATE_HEATED_INIT" />
    <result column="RENEW_INIT" property="RENEW_INIT" />
    <result column="DATE_RENEW_INIT" property="DATE_RENEW_INIT" />
    <result column="RELATED_TO_BR" property="RELATED_TO_BR" />
    <result column="POSTAL_CODE1" property="POSTAL_CODE1" />
    <result column="MAILING_POSTAL_CODE1" property="MAILING_POSTAL_CODE1" />
    <result column="POSTAL_CODE" property="POSTAL_CODE" />
    <result column="MAILING_POSTAL_CODE" property="MAILING_POSTAL_CODE" />
    <result column="REEDIT_PIN" property="REEDIT_PIN" />
    <result column="REEDIT_PIN_DATE" property="REEDIT_PIN_DATE" />
    <result column="PARENT_CARD" property="PARENT_CARD" />
    <result column="PARENT_APP_REF" property="PARENT_APP_REF" />
    <result column="ACTION" property="ACTION" />
    <result column="CARD_ALERT_STATUS" property="CARD_ALERT_STATUS" />
    <result column="ORIGINAL_CARD_NO" property="ORIGINAL_CARD_NO" />
    <result column="BATCH_NO1" property="BATCH_NO1" />
    <result column="PURCHASER_ID_TYPE" property="PURCHASER_ID_TYPE" />
    <result column="RECEIVER_ID_TYPE" property="RECEIVER_ID_TYPE" />
    <result column="RELATED_TO" property="RELATED_TO" />
    <result column="ADDRESS_1" property="ADDRESS_1" />
    <result column="ADDRESS_2" property="ADDRESS_2" />
    <result column="ADDRESS_3" property="ADDRESS_3" />
    <result column="COUNTRY" property="COUNTRY" />
    <result column="NO_LIABILITY" property="NO_LIABILITY" />
    <result column="REPLACE_REISSUE" property="REPLACE_REISSUE" />
    <result column="APPLY_REASON" property="APPLY_REASON" />
    <result column="CIF_HOLDER" property="CIF_HOLDER" />
    <result column="COUNTRY_CODE" property="COUNTRY_CODE" />
    <result column="HOLD_FOR_RENEWAL" property="HOLD_FOR_RENEWAL" />
    <result column="MAX_BAL" property="MAX_BAL" />
    <result column="PREV_EXP_DATE" property="PREV_EXP_DATE" />
    <result column="PREV_STATUS" property="PREV_STATUS" />
    <result column="SOURCE_INCOME" property="SOURCE_INCOME" />
    <result column="CARD_MESSAGE" property="CARD_MESSAGE" />
    <result column="DESIGN" property="DESIGN" />
    <result column="MESSAGE_INFO" property="MESSAGE_INFO" />
    <result column="PURCHASER_EMAIL" property="PURCHASER_EMAIL" />
    <result column="PURCHASER_ID_NO" property="PURCHASER_ID_NO" />
    <result column="PURCHASER_NAME" property="PURCHASER_NAME" />
    <result column="PURCHASER_PHONE" property="PURCHASER_PHONE" />
    <result column="RECEIVER_EMAIL" property="RECEIVER_EMAIL" />
    <result column="RECEIVER_ID_NO" property="RECEIVER_ID_NO" />
    <result column="RECEIVER_NAME" property="RECEIVER_NAME" />
    <result column="RECEIVER_PHONE" property="RECEIVER_PHONE" />
    <result column="BIOMETRIC_APPROVED_YN" property="BIOMETRIC_APPROVED_YN" />
    <result column="CARD_READER_SRL" property="CARD_READER_SRL" />
  </resultMap>
  <sql id="Base_Column_List" >
    APPLICATION_ID, BRANCH_CODE, COMP_CODE, REFERENCE, CARD_TYPE, CIF, CIF_STATUS, CIF_STATUS_REASON, 
    CIF_STATUS_DATE, EFFECTIVE_DATE, EXPIRY_DATE, PREPARATION_DATE, STATUS, STATUS_REASON, 
    DATE_CREATED, CREATED_BY, DATE_APPROVED, APPROVED_BY, DATE_ISSUED, ISSUED_BY, DATE_ACTIVATED, 
    ACTIVATED_BY, DATE_BLOCKED, BLOCKED_BY, DATE_MONITORED, MONITORED_BY, DATE_DEACTIVATED, 
    DEACTIVATED_BY, DATE_CANCELLED, CANCELLED_BY, DATE_REPLACED, REPLACED_BY, LAST_STATUS, 
    NEW_EFFECTIVE_DATE, NEW_EXPIRY_DATE, NEW_PREPARATION_DATE, DATE_MODIFIED, MODIFIED_BY, 
    DATE_DELETED, DELETED_BY, DATE_RENEWED, RENEWED_BY, PROCESSED, CARD_NO, PAYMENT_PERC, 
    CARD_HOLDER_NAME, REASON_DESC_ENG, REASON_DESC_ARAB, PRIM_SUPP, DATE_HEATED, HEATED_BY, 
    DEST_BRANCH, DELIVERED_DATE, DELIVERED_LOC, TELLER_CODE, BATCH_NO, USER_ID, CTS_TRS_NO, 
    CIVIL_ID, DEBIT_DAYS, FREE_CARD, LIEN_INFORMATION, SENT_KNET, DESTROYED_BY, DATE_DESTROYED, 
    UNBLOCKED_BY, DATE_UNBLOCKED, ID_TYPE, NATION_CODE, DATE_BIRTH, TEL_NO, POBOX_AREA, 
    PO_BOX, OCCUP_POSITION, DEPT, EMPL_DURATION, EMP_TEL, MONTHLY_SALARY, EDUC_LEVEL, 
    CREDIT_TYPE, BILLING_ACC, BANK_NAME, ACCOUNT_NUMBER, DIVISION, CINET_CHECKED, DATE_APPLIED, 
    APPLIED_BY, DATE_RECOMMEND, RECOMMEND_BY, DATE_REJECTED, REJECTED_BY, DATE_REVISED, 
    REVISED_BY, PAYMENT_DATE, PAYMENT_AMOUNT, NEXT_BILLING_DATE, EMAIL, LIEN_ACC, OUTSTANDING_BALANCE, 
    LAST_LIMIT_INCREASE, MAILING_REGION, MAILING_ADDRESS1, MAILING_ADDRESS2, MAILING_ADDRESS3, 
    MAILING_ADDRESS4, MAILING_CITY, MAILING_COUNTRY, MAILING_POBOX_AREA, MAILING_PO_BOX, 
    NO_OF_CARDS, IS_RENEWED, EMPLOYER_NAME, REMAINING_AMOUNT, TOTAL_LIMIT, SEXE, DATE_MODIFIED_1, 
    MODIFIED_BY_1, APP_REF, LIMIT_BASED_ON, LIMIT_CHECK_PERIOD, POS_LIMIT_BASED_ON, POS_LIMIT_CHECK_PERIOD, 
    POS_LIMIT_AMOUNT, SENT_TO_PROV_BY, DATE_SENT_TO_PROV, RECEIVED_FROM_PROV_BY, DATE_RECEIVED_FROM_PROV, 
    RECEIVED_BY_BRANCH_BY, DATE_RECEIVED_BY_BRANCH, ISSUED_INIT, DATE_ISSUED_INIT, ACTIVATED_INIT, 
    DATE_ACTIVATED_INIT, MONITORED_INIT, DATE_MONITORED_INIT, DEACTIVATED_INIT, DATE_DEACTIVATED_INIT, 
    DESTROYED_INIT, DATE_DESTROYED_INIT, REPLACED_INIT, DATE_REPLACED_INIT, CANCELLED_INIT, 
    DATE_CANCELLED_INIT, BLOCKED_INIT, DATE_BLOCKED_INIT, UNBLOCKED_INIT, DATE_UNBLOCKED_INIT, 
    HEATED_INIT, DATE_HEATED_INIT, RENEW_INIT, DATE_RENEW_INIT, RELATED_TO_BR, POSTAL_CODE1, 
    MAILING_POSTAL_CODE1, POSTAL_CODE, MAILING_POSTAL_CODE, REEDIT_PIN, REEDIT_PIN_DATE, 
    PARENT_CARD, PARENT_APP_REF, ACTION, CARD_ALERT_STATUS, ORIGINAL_CARD_NO, BATCH_NO1, 
    PURCHASER_ID_TYPE, RECEIVER_ID_TYPE, RELATED_TO, ADDRESS_1, ADDRESS_2, ADDRESS_3, 
    COUNTRY, NO_LIABILITY, REPLACE_REISSUE, APPLY_REASON, CIF_HOLDER, COUNTRY_CODE, HOLD_FOR_RENEWAL, 
    MAX_BAL, PREV_EXP_DATE, PREV_STATUS, SOURCE_INCOME, CARD_MESSAGE, DESIGN, MESSAGE_INFO, 
    PURCHASER_EMAIL, PURCHASER_ID_NO, PURCHASER_NAME, PURCHASER_PHONE, RECEIVER_EMAIL, 
    RECEIVER_ID_NO, RECEIVER_NAME, RECEIVER_PHONE,BIOMETRIC_APPROVED_YN,CARD_READER_SRL
  </sql>
  <select id="selectCTSCARDS_MGT_ALERT" resultMap="BaseResultMap" parameterType="com.path.dbmaps.vo.CTSCARDS_MGT_ALERTVOKey" >
    select 
    <include refid="Base_Column_List" />
    from CTSCARDS_MGT_ALERT
    where APPLICATION_ID = #{APPLICATION_ID}
      and BRANCH_CODE = #{BRANCH_CODE}
      and COMP_CODE = #{COMP_CODE}
  </select>
  <delete id="deleteCTSCARDS_MGT_ALERT" parameterType="com.path.dbmaps.vo.CTSCARDS_MGT_ALERTVOKey" >
    delete from CTSCARDS_MGT_ALERT
    where APPLICATION_ID = #{APPLICATION_ID}
      and BRANCH_CODE = #{BRANCH_CODE}
      and COMP_CODE = #{COMP_CODE}
  </delete>
  <insert id="insertCTSCARDS_MGT_ALERT" parameterType="com.path.dbmaps.vo.CTSCARDS_MGT_ALERTVO" >
    insert into CTSCARDS_MGT_ALERT
    <trim prefix="(" suffix=")" suffixOverrides="," >
      <if test="APPLICATION_ID != null and APPLICATION_ID != emptyBigDecimalValue" >
        APPLICATION_ID,
      </if>
      <if test="BRANCH_CODE != null and BRANCH_CODE != emptyBigDecimalValue" >
        BRANCH_CODE,
      </if>
      <if test="COMP_CODE != null and COMP_CODE != emptyBigDecimalValue" >
        COMP_CODE,
      </if>
      <if test="REFERENCE != null" >
        REFERENCE,
      </if>
      <if test="CARD_TYPE != null and CARD_TYPE != emptyBigDecimalValue" >
        CARD_TYPE,
      </if>
      <if test="CIF != null and CIF != emptyBigDecimalValue" >
        CIF,
      </if>
      <if test="CIF_STATUS != null" >
        CIF_STATUS,
      </if>
      <if test="CIF_STATUS_REASON != null" >
        CIF_STATUS_REASON,
      </if>
      <if test="CIF_STATUS_DATE != null" >
        CIF_STATUS_DATE,
      </if>
      <if test="EFFECTIVE_DATE != null" >
        EFFECTIVE_DATE,
      </if>
      <if test="EXPIRY_DATE != null" >
        EXPIRY_DATE,
      </if>
      <if test="PREPARATION_DATE != null" >
        PREPARATION_DATE,
      </if>
      <if test="STATUS != null" >
        STATUS,
      </if>
      <if test="STATUS_REASON != null" >
        STATUS_REASON,
      </if>
      <if test="DATE_CREATED != null" >
        DATE_CREATED,
      </if>
      <if test="CREATED_BY != null" >
        CREATED_BY,
      </if>
      <if test="DATE_APPROVED != null" >
        DATE_APPROVED,
      </if>
      <if test="APPROVED_BY != null" >
        APPROVED_BY,
      </if>
      <if test="DATE_ISSUED != null" >
        DATE_ISSUED,
      </if>
      <if test="ISSUED_BY != null" >
        ISSUED_BY,
      </if>
      <if test="DATE_ACTIVATED != null" >
        DATE_ACTIVATED,
      </if>
      <if test="ACTIVATED_BY != null" >
        ACTIVATED_BY,
      </if>
      <if test="DATE_BLOCKED != null" >
        DATE_BLOCKED,
      </if>
      <if test="BLOCKED_BY != null" >
        BLOCKED_BY,
      </if>
      <if test="DATE_MONITORED != null" >
        DATE_MONITORED,
      </if>
      <if test="MONITORED_BY != null" >
        MONITORED_BY,
      </if>
      <if test="DATE_DEACTIVATED != null" >
        DATE_DEACTIVATED,
      </if>
      <if test="DEACTIVATED_BY != null" >
        DEACTIVATED_BY,
      </if>
      <if test="DATE_CANCELLED != null" >
        DATE_CANCELLED,
      </if>
      <if test="CANCELLED_BY != null" >
        CANCELLED_BY,
      </if>
      <if test="DATE_REPLACED != null" >
        DATE_REPLACED,
      </if>
      <if test="REPLACED_BY != null" >
        REPLACED_BY,
      </if>
      <if test="LAST_STATUS != null" >
        LAST_STATUS,
      </if>
      <if test="NEW_EFFECTIVE_DATE != null" >
        NEW_EFFECTIVE_DATE,
      </if>
      <if test="NEW_EXPIRY_DATE != null" >
        NEW_EXPIRY_DATE,
      </if>
      <if test="NEW_PREPARATION_DATE != null" >
        NEW_PREPARATION_DATE,
      </if>
      <if test="DATE_MODIFIED != null" >
        DATE_MODIFIED,
      </if>
      <if test="MODIFIED_BY != null" >
        MODIFIED_BY,
      </if>
      <if test="DATE_DELETED != null" >
        DATE_DELETED,
      </if>
      <if test="DELETED_BY != null" >
        DELETED_BY,
      </if>
      <if test="DATE_RENEWED != null" >
        DATE_RENEWED,
      </if>
      <if test="RENEWED_BY != null" >
        RENEWED_BY,
      </if>
      <if test="PROCESSED != null" >
        PROCESSED,
      </if>
      <if test="CARD_NO != null" >
        CARD_NO,
      </if>
      <if test="PAYMENT_PERC != null and PAYMENT_PERC != emptyBigDecimalValue" >
        PAYMENT_PERC,
      </if>
      <if test="CARD_HOLDER_NAME != null" >
        CARD_HOLDER_NAME,
      </if>
      <if test="REASON_DESC_ENG != null" >
        REASON_DESC_ENG,
      </if>
      <if test="REASON_DESC_ARAB != null" >
        REASON_DESC_ARAB,
      </if>
      <if test="PRIM_SUPP != null" >
        PRIM_SUPP,
      </if>
      <if test="DATE_HEATED != null" >
        DATE_HEATED,
      </if>
      <if test="HEATED_BY != null" >
        HEATED_BY,
      </if>
      <if test="DEST_BRANCH != null and DEST_BRANCH != emptyBigDecimalValue" >
        DEST_BRANCH,
      </if>
      <if test="DELIVERED_DATE != null" >
        DELIVERED_DATE,
      </if>
      <if test="DELIVERED_LOC != null" >
        DELIVERED_LOC,
      </if>
      <if test="TELLER_CODE != null and TELLER_CODE != emptyBigDecimalValue" >
        TELLER_CODE,
      </if>
      <if test="BATCH_NO != null" >
        BATCH_NO,
      </if>
      <if test="USER_ID != null" >
        USER_ID,
      </if>
      <if test="CTS_TRS_NO != null and CTS_TRS_NO != emptyBigDecimalValue" >
        CTS_TRS_NO,
      </if>
      <if test="CIVIL_ID != null" >
        CIVIL_ID,
      </if>
      <if test="DEBIT_DAYS != null and DEBIT_DAYS != emptyBigDecimalValue" >
        DEBIT_DAYS,
      </if>
      <if test="FREE_CARD != null" >
        FREE_CARD,
      </if>
      <if test="LIEN_INFORMATION != null" >
        LIEN_INFORMATION,
      </if>
      <if test="SENT_KNET != null" >
        SENT_KNET,
      </if>
      <if test="DESTROYED_BY != null" >
        DESTROYED_BY,
      </if>
      <if test="DATE_DESTROYED != null" >
        DATE_DESTROYED,
      </if>
      <if test="UNBLOCKED_BY != null" >
        UNBLOCKED_BY,
      </if>
      <if test="DATE_UNBLOCKED != null" >
        DATE_UNBLOCKED,
      </if>
      <if test="ID_TYPE != null and ID_TYPE != emptyBigDecimalValue" >
        ID_TYPE,
      </if>
      <if test="NATION_CODE != null and NATION_CODE != emptyBigDecimalValue" >
        NATION_CODE,
      </if>
      <if test="DATE_BIRTH != null" >
        DATE_BIRTH,
      </if>
      <if test="TEL_NO != null" >
        TEL_NO,
      </if>
      <if test="POBOX_AREA != null and POBOX_AREA != emptyBigDecimalValue" >
        POBOX_AREA,
      </if>
      <if test="PO_BOX != null" >
        PO_BOX,
      </if>
      <if test="OCCUP_POSITION != null and OCCUP_POSITION != emptyBigDecimalValue" >
        OCCUP_POSITION,
      </if>
      <if test="DEPT != null and DEPT != emptyBigDecimalValue" >
        DEPT,
      </if>
      <if test="EMPL_DURATION != null and EMPL_DURATION != emptyBigDecimalValue" >
        EMPL_DURATION,
      </if>
      <if test="EMP_TEL != null" >
        EMP_TEL,
      </if>
      <if test="MONTHLY_SALARY != null and MONTHLY_SALARY != emptyBigDecimalValue" >
        MONTHLY_SALARY,
      </if>
      <if test="EDUC_LEVEL != null and EDUC_LEVEL != emptyBigDecimalValue" >
        EDUC_LEVEL,
      </if>
      <if test="CREDIT_TYPE != null and CREDIT_TYPE != emptyBigDecimalValue" >
        CREDIT_TYPE,
      </if>
      <if test="BILLING_ACC != null and BILLING_ACC != emptyBigDecimalValue" >
        BILLING_ACC,
      </if>
      <if test="BANK_NAME != null" >
        BANK_NAME,
      </if>
      <if test="ACCOUNT_NUMBER != null" >
        ACCOUNT_NUMBER,
      </if>
      <if test="DIVISION != null and DIVISION != emptyBigDecimalValue" >
        DIVISION,
      </if>
      <if test="CINET_CHECKED != null" >
        CINET_CHECKED,
      </if>
      <if test="DATE_APPLIED != null" >
        DATE_APPLIED,
      </if>
      <if test="APPLIED_BY != null" >
        APPLIED_BY,
      </if>
      <if test="DATE_RECOMMEND != null" >
        DATE_RECOMMEND,
      </if>
      <if test="RECOMMEND_BY != null" >
        RECOMMEND_BY,
      </if>
      <if test="DATE_REJECTED != null" >
        DATE_REJECTED,
      </if>
      <if test="REJECTED_BY != null" >
        REJECTED_BY,
      </if>
      <if test="DATE_REVISED != null" >
        DATE_REVISED,
      </if>
      <if test="REVISED_BY != null" >
        REVISED_BY,
      </if>
      <if test="PAYMENT_DATE != null" >
        PAYMENT_DATE,
      </if>
      <if test="PAYMENT_AMOUNT != null and PAYMENT_AMOUNT != emptyBigDecimalValue" >
        PAYMENT_AMOUNT,
      </if>
      <if test="NEXT_BILLING_DATE != null" >
        NEXT_BILLING_DATE,
      </if>
      <if test="EMAIL != null" >
        EMAIL,
      </if>
      <if test="LIEN_ACC != null" >
        LIEN_ACC,
      </if>
      <if test="OUTSTANDING_BALANCE != null and OUTSTANDING_BALANCE != emptyBigDecimalValue" >
        OUTSTANDING_BALANCE,
      </if>
      <if test="LAST_LIMIT_INCREASE != null and LAST_LIMIT_INCREASE != emptyBigDecimalValue" >
        LAST_LIMIT_INCREASE,
      </if>
      <if test="MAILING_REGION != null and MAILING_REGION != emptyBigDecimalValue" >
        MAILING_REGION,
      </if>
      <if test="MAILING_ADDRESS1 != null" >
        MAILING_ADDRESS1,
      </if>
      <if test="MAILING_ADDRESS2 != null" >
        MAILING_ADDRESS2,
      </if>
      <if test="MAILING_ADDRESS3 != null" >
        MAILING_ADDRESS3,
      </if>
      <if test="MAILING_ADDRESS4 != null" >
        MAILING_ADDRESS4,
      </if>
      <if test="MAILING_CITY != null" >
        MAILING_CITY,
      </if>
      <if test="MAILING_COUNTRY != null and MAILING_COUNTRY != emptyBigDecimalValue" >
        MAILING_COUNTRY,
      </if>
      <if test="MAILING_POBOX_AREA != null and MAILING_POBOX_AREA != emptyBigDecimalValue" >
        MAILING_POBOX_AREA,
      </if>
      <if test="MAILING_PO_BOX != null" >
        MAILING_PO_BOX,
      </if>
      <if test="NO_OF_CARDS != null and NO_OF_CARDS != emptyBigDecimalValue" >
        NO_OF_CARDS,
      </if>
      <if test="IS_RENEWED != null" >
        IS_RENEWED,
      </if>
      <if test="EMPLOYER_NAME != null" >
        EMPLOYER_NAME,
      </if>
      <if test="REMAINING_AMOUNT != null and REMAINING_AMOUNT != emptyBigDecimalValue" >
        REMAINING_AMOUNT,
      </if>
      <if test="TOTAL_LIMIT != null and TOTAL_LIMIT != emptyBigDecimalValue" >
        TOTAL_LIMIT,
      </if>
      <if test="SEXE != null" >
        SEXE,
      </if>
      <if test="DATE_MODIFIED_1 != null" >
        DATE_MODIFIED_1,
      </if>
      <if test="MODIFIED_BY_1 != null" >
        MODIFIED_BY_1,
      </if>
      <if test="APP_REF != null and APP_REF != emptyBigDecimalValue" >
        APP_REF,
      </if>
      <if test="LIMIT_BASED_ON != null" >
        LIMIT_BASED_ON,
      </if>
      <if test="LIMIT_CHECK_PERIOD != null" >
        LIMIT_CHECK_PERIOD,
      </if>
      <if test="POS_LIMIT_BASED_ON != null" >
        POS_LIMIT_BASED_ON,
      </if>
      <if test="POS_LIMIT_CHECK_PERIOD != null" >
        POS_LIMIT_CHECK_PERIOD,
      </if>
      <if test="POS_LIMIT_AMOUNT != null and POS_LIMIT_AMOUNT != emptyBigDecimalValue" >
        POS_LIMIT_AMOUNT,
      </if>
      <if test="SENT_TO_PROV_BY != null" >
        SENT_TO_PROV_BY,
      </if>
      <if test="DATE_SENT_TO_PROV != null" >
        DATE_SENT_TO_PROV,
      </if>
      <if test="RECEIVED_FROM_PROV_BY != null" >
        RECEIVED_FROM_PROV_BY,
      </if>
      <if test="DATE_RECEIVED_FROM_PROV != null" >
        DATE_RECEIVED_FROM_PROV,
      </if>
      <if test="RECEIVED_BY_BRANCH_BY != null" >
        RECEIVED_BY_BRANCH_BY,
      </if>
      <if test="DATE_RECEIVED_BY_BRANCH != null" >
        DATE_RECEIVED_BY_BRANCH,
      </if>
      <if test="ISSUED_INIT != null" >
        ISSUED_INIT,
      </if>
      <if test="DATE_ISSUED_INIT != null" >
        DATE_ISSUED_INIT,
      </if>
      <if test="ACTIVATED_INIT != null" >
        ACTIVATED_INIT,
      </if>
      <if test="DATE_ACTIVATED_INIT != null" >
        DATE_ACTIVATED_INIT,
      </if>
      <if test="MONITORED_INIT != null" >
        MONITORED_INIT,
      </if>
      <if test="DATE_MONITORED_INIT != null" >
        DATE_MONITORED_INIT,
      </if>
      <if test="DEACTIVATED_INIT != null" >
        DEACTIVATED_INIT,
      </if>
      <if test="DATE_DEACTIVATED_INIT != null" >
        DATE_DEACTIVATED_INIT,
      </if>
      <if test="DESTROYED_INIT != null" >
        DESTROYED_INIT,
      </if>
      <if test="DATE_DESTROYED_INIT != null" >
        DATE_DESTROYED_INIT,
      </if>
      <if test="REPLACED_INIT != null" >
        REPLACED_INIT,
      </if>
      <if test="DATE_REPLACED_INIT != null" >
        DATE_REPLACED_INIT,
      </if>
      <if test="CANCELLED_INIT != null" >
        CANCELLED_INIT,
      </if>
      <if test="DATE_CANCELLED_INIT != null" >
        DATE_CANCELLED_INIT,
      </if>
      <if test="BLOCKED_INIT != null" >
        BLOCKED_INIT,
      </if>
      <if test="DATE_BLOCKED_INIT != null" >
        DATE_BLOCKED_INIT,
      </if>
      <if test="UNBLOCKED_INIT != null" >
        UNBLOCKED_INIT,
      </if>
      <if test="DATE_UNBLOCKED_INIT != null" >
        DATE_UNBLOCKED_INIT,
      </if>
      <if test="HEATED_INIT != null" >
        HEATED_INIT,
      </if>
      <if test="DATE_HEATED_INIT != null" >
        DATE_HEATED_INIT,
      </if>
      <if test="RENEW_INIT != null" >
        RENEW_INIT,
      </if>
      <if test="DATE_RENEW_INIT != null" >
        DATE_RENEW_INIT,
      </if>
      <if test="RELATED_TO_BR != null and RELATED_TO_BR != emptyBigDecimalValue" >
        RELATED_TO_BR,
      </if>
      <if test="POSTAL_CODE1 != null" >
        POSTAL_CODE1,
      </if>
      <if test="MAILING_POSTAL_CODE1 != null" >
        MAILING_POSTAL_CODE1,
      </if>
      <if test="POSTAL_CODE != null and POSTAL_CODE != emptyBigDecimalValue" >
        POSTAL_CODE,
      </if>
      <if test="MAILING_POSTAL_CODE != null and MAILING_POSTAL_CODE != emptyBigDecimalValue" >
        MAILING_POSTAL_CODE,
      </if>
      <if test="REEDIT_PIN != null" >
        REEDIT_PIN,
      </if>
      <if test="REEDIT_PIN_DATE != null" >
        REEDIT_PIN_DATE,
      </if>
      <if test="PARENT_CARD != null" >
        PARENT_CARD,
      </if>
      <if test="PARENT_APP_REF != null and PARENT_APP_REF != emptyBigDecimalValue" >
        PARENT_APP_REF,
      </if>
      <if test="ACTION != null" >
        ACTION,
      </if>
      <if test="CARD_ALERT_STATUS != null" >
        CARD_ALERT_STATUS,
      </if>
      <if test="ORIGINAL_CARD_NO != null" >
        ORIGINAL_CARD_NO,
      </if>
      <if test="BATCH_NO1 != null" >
        BATCH_NO1,
      </if>
      <if test="PURCHASER_ID_TYPE != null and PURCHASER_ID_TYPE != emptyBigDecimalValue" >
        PURCHASER_ID_TYPE,
      </if>
      <if test="RECEIVER_ID_TYPE != null and RECEIVER_ID_TYPE != emptyBigDecimalValue" >
        RECEIVER_ID_TYPE,
      </if>
      <if test="RELATED_TO != null and RELATED_TO != emptyBigDecimalValue" >
        RELATED_TO,
      </if>
      <if test="ADDRESS_1 != null" >
        ADDRESS_1,
      </if>
      <if test="ADDRESS_2 != null" >
        ADDRESS_2,
      </if>
      <if test="ADDRESS_3 != null" >
        ADDRESS_3,
      </if>
      <if test="COUNTRY != null" >
        COUNTRY,
      </if>
      <if test="NO_LIABILITY != null" >
        NO_LIABILITY,
      </if>
      <if test="REPLACE_REISSUE != null" >
        REPLACE_REISSUE,
      </if>
      <if test="APPLY_REASON != null" >
        APPLY_REASON,
      </if>
      <if test="CIF_HOLDER != null and CIF_HOLDER != emptyBigDecimalValue" >
        CIF_HOLDER,
      </if>
      <if test="COUNTRY_CODE != null and COUNTRY_CODE != emptyBigDecimalValue" >
        COUNTRY_CODE,
      </if>
      <if test="HOLD_FOR_RENEWAL != null" >
        HOLD_FOR_RENEWAL,
      </if>
      <if test="MAX_BAL != null and MAX_BAL != emptyBigDecimalValue" >
        MAX_BAL,
      </if>
      <if test="PREV_EXP_DATE != null" >
        PREV_EXP_DATE,
      </if>
      <if test="PREV_STATUS != null" >
        PREV_STATUS,
      </if>
      <if test="SOURCE_INCOME != null" >
        SOURCE_INCOME,
      </if>
      <if test="CARD_MESSAGE != null and CARD_MESSAGE != emptyBigDecimalValue" >
        CARD_MESSAGE,
      </if>
      <if test="DESIGN != null and DESIGN != emptyBigDecimalValue" >
        DESIGN,
      </if>
      <if test="MESSAGE_INFO != null" >
        MESSAGE_INFO,
      </if>
      <if test="PURCHASER_EMAIL != null" >
        PURCHASER_EMAIL,
      </if>
      <if test="PURCHASER_ID_NO != null" >
        PURCHASER_ID_NO,
      </if>
      <if test="PURCHASER_NAME != null" >
        PURCHASER_NAME,
      </if>
      <if test="PURCHASER_PHONE != null" >
        PURCHASER_PHONE,
      </if>
      <if test="RECEIVER_EMAIL != null" >
        RECEIVER_EMAIL,
      </if>
      <if test="RECEIVER_ID_NO != null" >
        RECEIVER_ID_NO,
      </if>
      <if test="RECEIVER_NAME != null" >
        RECEIVER_NAME,
      </if>
      <if test="RECEIVER_PHONE != null" >
        RECEIVER_PHONE,
      </if>
       <if test="BIOMETRIC_APPROVED_YN != null" >
        BIOMETRIC_APPROVED_YN,
      </if>
        <if test="CARD_READER_SRL != null" >
        CARD_READER_SRL,
      </if>
    </trim>
    <trim prefix="values (" suffix=")" suffixOverrides="," >
      <if test="APPLICATION_ID != null and APPLICATION_ID != emptyBigDecimalValue" >
        #{APPLICATION_ID},
      </if>
      <if test="BRANCH_CODE != null and BRANCH_CODE != emptyBigDecimalValue" >
        #{BRANCH_CODE},
      </if>
      <if test="COMP_CODE != null and COMP_CODE != emptyBigDecimalValue" >
        #{COMP_CODE},
      </if>
      <if test="REFERENCE != null" >
        #{REFERENCE},
      </if>
      <if test="CARD_TYPE != null and CARD_TYPE != emptyBigDecimalValue" >
        #{CARD_TYPE},
      </if>
      <if test="CIF != null and CIF != emptyBigDecimalValue" >
        #{CIF},
      </if>
      <if test="CIF_STATUS != null" >
        #{CIF_STATUS},
      </if>
      <if test="CIF_STATUS_REASON != null" >
        #{CIF_STATUS_REASON},
      </if>
      <if test="CIF_STATUS_DATE != null" >
        #{CIF_STATUS_DATE},
      </if>
      <if test="EFFECTIVE_DATE != null" >
        #{EFFECTIVE_DATE},
      </if>
      <if test="EXPIRY_DATE != null" >
        #{EXPIRY_DATE},
      </if>
      <if test="PREPARATION_DATE != null" >
        #{PREPARATION_DATE},
      </if>
      <if test="STATUS != null" >
        #{STATUS},
      </if>
      <if test="STATUS_REASON != null" >
        #{STATUS_REASON},
      </if>
      <if test="DATE_CREATED != null" >
        #{DATE_CREATED},
      </if>
      <if test="CREATED_BY != null" >
        #{CREATED_BY},
      </if>
      <if test="DATE_APPROVED != null" >
        #{DATE_APPROVED},
      </if>
      <if test="APPROVED_BY != null" >
        #{APPROVED_BY},
      </if>
      <if test="DATE_ISSUED != null" >
        #{DATE_ISSUED},
      </if>
      <if test="ISSUED_BY != null" >
        #{ISSUED_BY},
      </if>
      <if test="DATE_ACTIVATED != null" >
        #{DATE_ACTIVATED},
      </if>
      <if test="ACTIVATED_BY != null" >
        #{ACTIVATED_BY},
      </if>
      <if test="DATE_BLOCKED != null" >
        #{DATE_BLOCKED},
      </if>
      <if test="BLOCKED_BY != null" >
        #{BLOCKED_BY},
      </if>
      <if test="DATE_MONITORED != null" >
        #{DATE_MONITORED},
      </if>
      <if test="MONITORED_BY != null" >
        #{MONITORED_BY},
      </if>
      <if test="DATE_DEACTIVATED != null" >
        #{DATE_DEACTIVATED},
      </if>
      <if test="DEACTIVATED_BY != null" >
        #{DEACTIVATED_BY},
      </if>
      <if test="DATE_CANCELLED != null" >
        #{DATE_CANCELLED},
      </if>
      <if test="CANCELLED_BY != null" >
        #{CANCELLED_BY},
      </if>
      <if test="DATE_REPLACED != null" >
        #{DATE_REPLACED},
      </if>
      <if test="REPLACED_BY != null" >
        #{REPLACED_BY},
      </if>
      <if test="LAST_STATUS != null" >
        #{LAST_STATUS},
      </if>
      <if test="NEW_EFFECTIVE_DATE != null" >
        #{NEW_EFFECTIVE_DATE},
      </if>
      <if test="NEW_EXPIRY_DATE != null" >
        #{NEW_EXPIRY_DATE},
      </if>
      <if test="NEW_PREPARATION_DATE != null" >
        #{NEW_PREPARATION_DATE},
      </if>
      <if test="DATE_MODIFIED != null" >
        #{DATE_MODIFIED},
      </if>
      <if test="MODIFIED_BY != null" >
        #{MODIFIED_BY},
      </if>
      <if test="DATE_DELETED != null" >
        #{DATE_DELETED},
      </if>
      <if test="DELETED_BY != null" >
        #{DELETED_BY},
      </if>
      <if test="DATE_RENEWED != null" >
        #{DATE_RENEWED},
      </if>
      <if test="RENEWED_BY != null" >
        #{RENEWED_BY},
      </if>
      <if test="PROCESSED != null" >
        #{PROCESSED},
      </if>
      <if test="CARD_NO != null" >
        #{CARD_NO},
      </if>
      <if test="PAYMENT_PERC != null and PAYMENT_PERC != emptyBigDecimalValue" >
        #{PAYMENT_PERC},
      </if>
      <if test="CARD_HOLDER_NAME != null" >
        #{CARD_HOLDER_NAME},
      </if>
      <if test="REASON_DESC_ENG != null" >
        #{REASON_DESC_ENG},
      </if>
      <if test="REASON_DESC_ARAB != null" >
        #{REASON_DESC_ARAB},
      </if>
      <if test="PRIM_SUPP != null" >
        #{PRIM_SUPP},
      </if>
      <if test="DATE_HEATED != null" >
        #{DATE_HEATED},
      </if>
      <if test="HEATED_BY != null" >
        #{HEATED_BY},
      </if>
      <if test="DEST_BRANCH != null and DEST_BRANCH != emptyBigDecimalValue" >
        #{DEST_BRANCH},
      </if>
      <if test="DELIVERED_DATE != null" >
        #{DELIVERED_DATE},
      </if>
      <if test="DELIVERED_LOC != null" >
        #{DELIVERED_LOC},
      </if>
      <if test="TELLER_CODE != null and TELLER_CODE != emptyBigDecimalValue" >
        #{TELLER_CODE},
      </if>
      <if test="BATCH_NO != null" >
        #{BATCH_NO},
      </if>
      <if test="USER_ID != null" >
        #{USER_ID},
      </if>
      <if test="CTS_TRS_NO != null and CTS_TRS_NO != emptyBigDecimalValue" >
        #{CTS_TRS_NO},
      </if>
      <if test="CIVIL_ID != null" >
        #{CIVIL_ID},
      </if>
      <if test="DEBIT_DAYS != null and DEBIT_DAYS != emptyBigDecimalValue" >
        #{DEBIT_DAYS},
      </if>
      <if test="FREE_CARD != null" >
        #{FREE_CARD},
      </if>
      <if test="LIEN_INFORMATION != null" >
        #{LIEN_INFORMATION},
      </if>
      <if test="SENT_KNET != null" >
        #{SENT_KNET},
      </if>
      <if test="DESTROYED_BY != null" >
        #{DESTROYED_BY},
      </if>
      <if test="DATE_DESTROYED != null" >
        #{DATE_DESTROYED},
      </if>
      <if test="UNBLOCKED_BY != null" >
        #{UNBLOCKED_BY},
      </if>
      <if test="DATE_UNBLOCKED != null" >
        #{DATE_UNBLOCKED},
      </if>
      <if test="ID_TYPE != null and ID_TYPE != emptyBigDecimalValue" >
        #{ID_TYPE},
      </if>
      <if test="NATION_CODE != null and NATION_CODE != emptyBigDecimalValue" >
        #{NATION_CODE},
      </if>
      <if test="DATE_BIRTH != null" >
        #{DATE_BIRTH},
      </if>
      <if test="TEL_NO != null" >
        #{TEL_NO},
      </if>
      <if test="POBOX_AREA != null and POBOX_AREA != emptyBigDecimalValue" >
        #{POBOX_AREA},
      </if>
      <if test="PO_BOX != null" >
        #{PO_BOX},
      </if>
      <if test="OCCUP_POSITION != null and OCCUP_POSITION != emptyBigDecimalValue" >
        #{OCCUP_POSITION},
      </if>
      <if test="DEPT != null and DEPT != emptyBigDecimalValue" >
        #{DEPT},
      </if>
      <if test="EMPL_DURATION != null and EMPL_DURATION != emptyBigDecimalValue" >
        #{EMPL_DURATION},
      </if>
      <if test="EMP_TEL != null" >
        #{EMP_TEL},
      </if>
      <if test="MONTHLY_SALARY != null and MONTHLY_SALARY != emptyBigDecimalValue" >
        #{MONTHLY_SALARY},
      </if>
      <if test="EDUC_LEVEL != null and EDUC_LEVEL != emptyBigDecimalValue" >
        #{EDUC_LEVEL},
      </if>
      <if test="CREDIT_TYPE != null and CREDIT_TYPE != emptyBigDecimalValue" >
        #{CREDIT_TYPE},
      </if>
      <if test="BILLING_ACC != null and BILLING_ACC != emptyBigDecimalValue" >
        #{BILLING_ACC},
      </if>
      <if test="BANK_NAME != null" >
        #{BANK_NAME},
      </if>
      <if test="ACCOUNT_NUMBER != null" >
        #{ACCOUNT_NUMBER},
      </if>
      <if test="DIVISION != null and DIVISION != emptyBigDecimalValue" >
        #{DIVISION},
      </if>
      <if test="CINET_CHECKED != null" >
        #{CINET_CHECKED},
      </if>
      <if test="DATE_APPLIED != null" >
        #{DATE_APPLIED},
      </if>
      <if test="APPLIED_BY != null" >
        #{APPLIED_BY},
      </if>
      <if test="DATE_RECOMMEND != null" >
        #{DATE_RECOMMEND},
      </if>
      <if test="RECOMMEND_BY != null" >
        #{RECOMMEND_BY},
      </if>
      <if test="DATE_REJECTED != null" >
        #{DATE_REJECTED},
      </if>
      <if test="REJECTED_BY != null" >
        #{REJECTED_BY},
      </if>
      <if test="DATE_REVISED != null" >
        #{DATE_REVISED},
      </if>
      <if test="REVISED_BY != null" >
        #{REVISED_BY},
      </if>
      <if test="PAYMENT_DATE != null" >
        #{PAYMENT_DATE},
      </if>
      <if test="PAYMENT_AMOUNT != null and PAYMENT_AMOUNT != emptyBigDecimalValue" >
        #{PAYMENT_AMOUNT},
      </if>
      <if test="NEXT_BILLING_DATE != null" >
        #{NEXT_BILLING_DATE},
      </if>
      <if test="EMAIL != null" >
        #{EMAIL},
      </if>
      <if test="LIEN_ACC != null" >
        #{LIEN_ACC},
      </if>
      <if test="OUTSTANDING_BALANCE != null and OUTSTANDING_BALANCE != emptyBigDecimalValue" >
        #{OUTSTANDING_BALANCE},
      </if>
      <if test="LAST_LIMIT_INCREASE != null and LAST_LIMIT_INCREASE != emptyBigDecimalValue" >
        #{LAST_LIMIT_INCREASE},
      </if>
      <if test="MAILING_REGION != null and MAILING_REGION != emptyBigDecimalValue" >
        #{MAILING_REGION},
      </if>
      <if test="MAILING_ADDRESS1 != null" >
        #{MAILING_ADDRESS1},
      </if>
      <if test="MAILING_ADDRESS2 != null" >
        #{MAILING_ADDRESS2},
      </if>
      <if test="MAILING_ADDRESS3 != null" >
        #{MAILING_ADDRESS3},
      </if>
      <if test="MAILING_ADDRESS4 != null" >
        #{MAILING_ADDRESS4},
      </if>
      <if test="MAILING_CITY != null" >
        #{MAILING_CITY},
      </if>
      <if test="MAILING_COUNTRY != null and MAILING_COUNTRY != emptyBigDecimalValue" >
        #{MAILING_COUNTRY},
      </if>
      <if test="MAILING_POBOX_AREA != null and MAILING_POBOX_AREA != emptyBigDecimalValue" >
        #{MAILING_POBOX_AREA},
      </if>
      <if test="MAILING_PO_BOX != null" >
        #{MAILING_PO_BOX},
      </if>
      <if test="NO_OF_CARDS != null and NO_OF_CARDS != emptyBigDecimalValue" >
        #{NO_OF_CARDS},
      </if>
      <if test="IS_RENEWED != null" >
        #{IS_RENEWED},
      </if>
      <if test="EMPLOYER_NAME != null" >
        #{EMPLOYER_NAME},
      </if>
      <if test="REMAINING_AMOUNT != null and REMAINING_AMOUNT != emptyBigDecimalValue" >
        #{REMAINING_AMOUNT},
      </if>
      <if test="TOTAL_LIMIT != null and TOTAL_LIMIT != emptyBigDecimalValue" >
        #{TOTAL_LIMIT},
      </if>
      <if test="SEXE != null" >
        #{SEXE},
      </if>
      <if test="DATE_MODIFIED_1 != null" >
        #{DATE_MODIFIED_1},
      </if>
      <if test="MODIFIED_BY_1 != null" >
        #{MODIFIED_BY_1},
      </if>
      <if test="APP_REF != null and APP_REF != emptyBigDecimalValue" >
        #{APP_REF},
      </if>
      <if test="LIMIT_BASED_ON != null" >
        #{LIMIT_BASED_ON},
      </if>
      <if test="LIMIT_CHECK_PERIOD != null" >
        #{LIMIT_CHECK_PERIOD},
      </if>
      <if test="POS_LIMIT_BASED_ON != null" >
        #{POS_LIMIT_BASED_ON},
      </if>
      <if test="POS_LIMIT_CHECK_PERIOD != null" >
        #{POS_LIMIT_CHECK_PERIOD},
      </if>
      <if test="POS_LIMIT_AMOUNT != null and POS_LIMIT_AMOUNT != emptyBigDecimalValue" >
        #{POS_LIMIT_AMOUNT},
      </if>
      <if test="SENT_TO_PROV_BY != null" >
        #{SENT_TO_PROV_BY},
      </if>
      <if test="DATE_SENT_TO_PROV != null" >
        #{DATE_SENT_TO_PROV},
      </if>
      <if test="RECEIVED_FROM_PROV_BY != null" >
        #{RECEIVED_FROM_PROV_BY},
      </if>
      <if test="DATE_RECEIVED_FROM_PROV != null" >
        #{DATE_RECEIVED_FROM_PROV},
      </if>
      <if test="RECEIVED_BY_BRANCH_BY != null" >
        #{RECEIVED_BY_BRANCH_BY},
      </if>
      <if test="DATE_RECEIVED_BY_BRANCH != null" >
        #{DATE_RECEIVED_BY_BRANCH},
      </if>
      <if test="ISSUED_INIT != null" >
        #{ISSUED_INIT},
      </if>
      <if test="DATE_ISSUED_INIT != null" >
        #{DATE_ISSUED_INIT},
      </if>
      <if test="ACTIVATED_INIT != null" >
        #{ACTIVATED_INIT},
      </if>
      <if test="DATE_ACTIVATED_INIT != null" >
        #{DATE_ACTIVATED_INIT},
      </if>
      <if test="MONITORED_INIT != null" >
        #{MONITORED_INIT},
      </if>
      <if test="DATE_MONITORED_INIT != null" >
        #{DATE_MONITORED_INIT},
      </if>
      <if test="DEACTIVATED_INIT != null" >
        #{DEACTIVATED_INIT},
      </if>
      <if test="DATE_DEACTIVATED_INIT != null" >
        #{DATE_DEACTIVATED_INIT},
      </if>
      <if test="DESTROYED_INIT != null" >
        #{DESTROYED_INIT},
      </if>
      <if test="DATE_DESTROYED_INIT != null" >
        #{DATE_DESTROYED_INIT},
      </if>
      <if test="REPLACED_INIT != null" >
        #{REPLACED_INIT},
      </if>
      <if test="DATE_REPLACED_INIT != null" >
        #{DATE_REPLACED_INIT},
      </if>
      <if test="CANCELLED_INIT != null" >
        #{CANCELLED_INIT},
      </if>
      <if test="DATE_CANCELLED_INIT != null" >
        #{DATE_CANCELLED_INIT},
      </if>
      <if test="BLOCKED_INIT != null" >
        #{BLOCKED_INIT},
      </if>
      <if test="DATE_BLOCKED_INIT != null" >
        #{DATE_BLOCKED_INIT},
      </if>
      <if test="UNBLOCKED_INIT != null" >
        #{UNBLOCKED_INIT},
      </if>
      <if test="DATE_UNBLOCKED_INIT != null" >
        #{DATE_UNBLOCKED_INIT},
      </if>
      <if test="HEATED_INIT != null" >
        #{HEATED_INIT},
      </if>
      <if test="DATE_HEATED_INIT != null" >
        #{DATE_HEATED_INIT},
      </if>
      <if test="RENEW_INIT != null" >
        #{RENEW_INIT},
      </if>
      <if test="DATE_RENEW_INIT != null" >
        #{DATE_RENEW_INIT},
      </if>
      <if test="RELATED_TO_BR != null and RELATED_TO_BR != emptyBigDecimalValue" >
        #{RELATED_TO_BR},
      </if>
      <if test="POSTAL_CODE1 != null" >
        #{POSTAL_CODE1},
      </if>
      <if test="MAILING_POSTAL_CODE1 != null" >
        #{MAILING_POSTAL_CODE1},
      </if>
      <if test="POSTAL_CODE != null and POSTAL_CODE != emptyBigDecimalValue" >
        #{POSTAL_CODE},
      </if>
      <if test="MAILING_POSTAL_CODE != null and MAILING_POSTAL_CODE != emptyBigDecimalValue" >
        #{MAILING_POSTAL_CODE},
      </if>
      <if test="REEDIT_PIN != null" >
        #{REEDIT_PIN},
      </if>
      <if test="REEDIT_PIN_DATE != null" >
        #{REEDIT_PIN_DATE},
      </if>
      <if test="PARENT_CARD != null" >
        #{PARENT_CARD},
      </if>
      <if test="PARENT_APP_REF != null and PARENT_APP_REF != emptyBigDecimalValue" >
        #{PARENT_APP_REF},
      </if>
      <if test="ACTION != null" >
        #{ACTION},
      </if>
      <if test="CARD_ALERT_STATUS != null" >
        #{CARD_ALERT_STATUS},
      </if>
      <if test="ORIGINAL_CARD_NO != null" >
        #{ORIGINAL_CARD_NO},
      </if>
      <if test="BATCH_NO1 != null" >
        #{BATCH_NO1},
      </if>
      <if test="PURCHASER_ID_TYPE != null and PURCHASER_ID_TYPE != emptyBigDecimalValue" >
        #{PURCHASER_ID_TYPE},
      </if>
      <if test="RECEIVER_ID_TYPE != null and RECEIVER_ID_TYPE != emptyBigDecimalValue" >
        #{RECEIVER_ID_TYPE},
      </if>
      <if test="RELATED_TO != null and RELATED_TO != emptyBigDecimalValue" >
        #{RELATED_TO},
      </if>
      <if test="ADDRESS_1 != null" >
        #{ADDRESS_1},
      </if>
      <if test="ADDRESS_2 != null" >
        #{ADDRESS_2},
      </if>
      <if test="ADDRESS_3 != null" >
        #{ADDRESS_3},
      </if>
      <if test="COUNTRY != null" >
        #{COUNTRY},
      </if>
      <if test="NO_LIABILITY != null" >
        #{NO_LIABILITY},
      </if>
      <if test="REPLACE_REISSUE != null" >
        #{REPLACE_REISSUE},
      </if>
      <if test="APPLY_REASON != null" >
        #{APPLY_REASON},
      </if>
      <if test="CIF_HOLDER != null and CIF_HOLDER != emptyBigDecimalValue" >
        #{CIF_HOLDER},
      </if>
      <if test="COUNTRY_CODE != null and COUNTRY_CODE != emptyBigDecimalValue" >
        #{COUNTRY_CODE},
      </if>
      <if test="HOLD_FOR_RENEWAL != null" >
        #{HOLD_FOR_RENEWAL},
      </if>
      <if test="MAX_BAL != null and MAX_BAL != emptyBigDecimalValue" >
        #{MAX_BAL},
      </if>
      <if test="PREV_EXP_DATE != null" >
        #{PREV_EXP_DATE},
      </if>
      <if test="PREV_STATUS != null" >
        #{PREV_STATUS},
      </if>
      <if test="SOURCE_INCOME != null" >
        #{SOURCE_INCOME},
      </if>
      <if test="CARD_MESSAGE != null and CARD_MESSAGE != emptyBigDecimalValue" >
        #{CARD_MESSAGE},
      </if>
      <if test="DESIGN != null and DESIGN != emptyBigDecimalValue" >
        #{DESIGN},
      </if>
      <if test="MESSAGE_INFO != null" >
        #{MESSAGE_INFO},
      </if>
      <if test="PURCHASER_EMAIL != null" >
        #{PURCHASER_EMAIL},
      </if>
      <if test="PURCHASER_ID_NO != null" >
        #{PURCHASER_ID_NO},
      </if>
      <if test="PURCHASER_NAME != null" >
        #{PURCHASER_NAME},
      </if>
      <if test="PURCHASER_PHONE != null" >
        #{PURCHASER_PHONE},
      </if>
      <if test="RECEIVER_EMAIL != null" >
        #{RECEIVER_EMAIL},
      </if>
      <if test="RECEIVER_ID_NO != null" >
        #{RECEIVER_ID_NO},
      </if>
      <if test="RECEIVER_NAME != null" >
        #{RECEIVER_NAME},
      </if>
      <if test="RECEIVER_PHONE != null" >
        #{RECEIVER_PHONE},
      </if>
      <if test="BIOMETRIC_APPROVED_YN != null" >
        #{BIOMETRIC_APPROVED_YN},
      </if>
       <if test="CARD_READER_SRL != null" >
        #{CARD_READER_SRL},
      </if>
    </trim>
  </insert>
  <sql id="sql_updateCTSCARDS_MGT_ALERT" >
    update CTSCARDS_MGT_ALERT
    <set >
      <if test="REFERENCE != null" >
        REFERENCE = #{REFERENCE},
      </if>
      <if test="CARD_TYPE != null" >
        <choose >
          <when test="CARD_TYPE == emptyBigDecimalValue" >
            CARD_TYPE = NULL ,
          </when>
          <otherwise >
            CARD_TYPE = #{CARD_TYPE},
          </otherwise>
        </choose>
      </if>
      <if test="CIF != null" >
        <choose >
          <when test="CIF == emptyBigDecimalValue" >
            CIF = NULL ,
          </when>
          <otherwise >
            CIF = #{CIF},
          </otherwise>
        </choose>
      </if>
      <if test="CIF_STATUS != null" >
        CIF_STATUS = #{CIF_STATUS},
      </if>
      <if test="CIF_STATUS_REASON != null" >
        CIF_STATUS_REASON = #{CIF_STATUS_REASON},
      </if>
      <if test="CIF_STATUS_DATE != null" >
        CIF_STATUS_DATE = #{CIF_STATUS_DATE},
      </if>
      <if test="EFFECTIVE_DATE != null" >
        EFFECTIVE_DATE = #{EFFECTIVE_DATE},
      </if>
      <if test="EXPIRY_DATE != null" >
        EXPIRY_DATE = #{EXPIRY_DATE},
      </if>
      <if test="PREPARATION_DATE != null" >
        PREPARATION_DATE = #{PREPARATION_DATE},
      </if>
      <if test="STATUS != null" >
        STATUS = #{STATUS},
      </if>
      <if test="STATUS_REASON != null" >
        STATUS_REASON = #{STATUS_REASON},
      </if>
      <if test="DATE_CREATED != null" >
        DATE_CREATED = #{DATE_CREATED},
      </if>
      <if test="CREATED_BY != null" >
        CREATED_BY = #{CREATED_BY},
      </if>
      <if test="DATE_APPROVED != null" >
        DATE_APPROVED = #{DATE_APPROVED},
      </if>
      <if test="APPROVED_BY != null" >
        APPROVED_BY = #{APPROVED_BY},
      </if>
      <if test="DATE_ISSUED != null" >
        DATE_ISSUED = #{DATE_ISSUED},
      </if>
      <if test="ISSUED_BY != null" >
        ISSUED_BY = #{ISSUED_BY},
      </if>
      <if test="DATE_ACTIVATED != null" >
        DATE_ACTIVATED = #{DATE_ACTIVATED},
      </if>
      <if test="ACTIVATED_BY != null" >
        ACTIVATED_BY = #{ACTIVATED_BY},
      </if>
      <if test="DATE_BLOCKED != null" >
        DATE_BLOCKED = #{DATE_BLOCKED},
      </if>
      <if test="BLOCKED_BY != null" >
        BLOCKED_BY = #{BLOCKED_BY},
      </if>
      <if test="DATE_MONITORED != null" >
        DATE_MONITORED = #{DATE_MONITORED},
      </if>
      <if test="MONITORED_BY != null" >
        MONITORED_BY = #{MONITORED_BY},
      </if>
      <if test="DATE_DEACTIVATED != null" >
        DATE_DEACTIVATED = #{DATE_DEACTIVATED},
      </if>
      <if test="DEACTIVATED_BY != null" >
        DEACTIVATED_BY = #{DEACTIVATED_BY},
      </if>
      <if test="DATE_CANCELLED != null" >
        DATE_CANCELLED = #{DATE_CANCELLED},
      </if>
      <if test="CANCELLED_BY != null" >
        CANCELLED_BY = #{CANCELLED_BY},
      </if>
      <if test="DATE_REPLACED != null" >
        DATE_REPLACED = #{DATE_REPLACED},
      </if>
      <if test="REPLACED_BY != null" >
        REPLACED_BY = #{REPLACED_BY},
      </if>
      <if test="LAST_STATUS != null" >
        LAST_STATUS = #{LAST_STATUS},
      </if>
      <if test="NEW_EFFECTIVE_DATE != null" >
        NEW_EFFECTIVE_DATE = #{NEW_EFFECTIVE_DATE},
      </if>
      <if test="NEW_EXPIRY_DATE != null" >
        NEW_EXPIRY_DATE = #{NEW_EXPIRY_DATE},
      </if>
      <if test="NEW_PREPARATION_DATE != null" >
        NEW_PREPARATION_DATE = #{NEW_PREPARATION_DATE},
      </if>
      <if test="DATE_MODIFIED != null" >
        DATE_MODIFIED = #{DATE_MODIFIED},
      </if>
      <if test="MODIFIED_BY != null" >
        MODIFIED_BY = #{MODIFIED_BY},
      </if>
      <if test="DATE_DELETED != null" >
        DATE_DELETED = #{DATE_DELETED},
      </if>
      <if test="DELETED_BY != null" >
        DELETED_BY = #{DELETED_BY},
      </if>
      <if test="DATE_RENEWED != null" >
        DATE_RENEWED = #{DATE_RENEWED},
      </if>
      <if test="RENEWED_BY != null" >
        RENEWED_BY = #{RENEWED_BY},
      </if>
      <if test="PROCESSED != null" >
        PROCESSED = #{PROCESSED},
      </if>
      <if test="CARD_NO != null" >
        CARD_NO = #{CARD_NO},
      </if>
      <if test="PAYMENT_PERC != null" >
        <choose >
          <when test="PAYMENT_PERC == emptyBigDecimalValue" >
            PAYMENT_PERC = NULL ,
          </when>
          <otherwise >
            PAYMENT_PERC = #{PAYMENT_PERC},
          </otherwise>
        </choose>
      </if>
      <if test="CARD_HOLDER_NAME != null" >
        CARD_HOLDER_NAME = #{CARD_HOLDER_NAME},
      </if>
      <if test="REASON_DESC_ENG != null" >
        REASON_DESC_ENG = #{REASON_DESC_ENG},
      </if>
      <if test="REASON_DESC_ARAB != null" >
        REASON_DESC_ARAB = #{REASON_DESC_ARAB},
      </if>
      <if test="PRIM_SUPP != null" >
        PRIM_SUPP = #{PRIM_SUPP},
      </if>
      <if test="DATE_HEATED != null" >
        DATE_HEATED = #{DATE_HEATED},
      </if>
      <if test="HEATED_BY != null" >
        HEATED_BY = #{HEATED_BY},
      </if>
      <if test="DEST_BRANCH != null" >
        <choose >
          <when test="DEST_BRANCH == emptyBigDecimalValue" >
            DEST_BRANCH = NULL ,
          </when>
          <otherwise >
            DEST_BRANCH = #{DEST_BRANCH},
          </otherwise>
        </choose>
      </if>
      <if test="DELIVERED_DATE != null" >
        DELIVERED_DATE = #{DELIVERED_DATE},
      </if>
      <if test="DELIVERED_LOC != null" >
        DELIVERED_LOC = #{DELIVERED_LOC},
      </if>
      <if test="TELLER_CODE != null" >
        <choose >
          <when test="TELLER_CODE == emptyBigDecimalValue" >
            TELLER_CODE = NULL ,
          </when>
          <otherwise >
            TELLER_CODE = #{TELLER_CODE},
          </otherwise>
        </choose>
      </if>
      <if test="BATCH_NO != null" >
        BATCH_NO = #{BATCH_NO},
      </if>
      <if test="USER_ID != null" >
        USER_ID = #{USER_ID},
      </if>
      <if test="CTS_TRS_NO != null" >
        <choose >
          <when test="CTS_TRS_NO == emptyBigDecimalValue" >
            CTS_TRS_NO = NULL ,
          </when>
          <otherwise >
            CTS_TRS_NO = #{CTS_TRS_NO},
          </otherwise>
        </choose>
      </if>
      <if test="CIVIL_ID != null" >
        CIVIL_ID = #{CIVIL_ID},
      </if>
      <if test="DEBIT_DAYS != null" >
        <choose >
          <when test="DEBIT_DAYS == emptyBigDecimalValue" >
            DEBIT_DAYS = NULL ,
          </when>
          <otherwise >
            DEBIT_DAYS = #{DEBIT_DAYS},
          </otherwise>
        </choose>
      </if>
      <if test="FREE_CARD != null" >
        FREE_CARD = #{FREE_CARD},
      </if>
      <if test="LIEN_INFORMATION != null" >
        LIEN_INFORMATION = #{LIEN_INFORMATION},
      </if>
      <if test="SENT_KNET != null" >
        SENT_KNET = #{SENT_KNET},
      </if>
      <if test="DESTROYED_BY != null" >
        DESTROYED_BY = #{DESTROYED_BY},
      </if>
      <if test="DATE_DESTROYED != null" >
        DATE_DESTROYED = #{DATE_DESTROYED},
      </if>
      <if test="UNBLOCKED_BY != null" >
        UNBLOCKED_BY = #{UNBLOCKED_BY},
      </if>
      <if test="DATE_UNBLOCKED != null" >
        DATE_UNBLOCKED = #{DATE_UNBLOCKED},
      </if>
      <if test="ID_TYPE != null" >
        <choose >
          <when test="ID_TYPE == emptyBigDecimalValue" >
            ID_TYPE = NULL ,
          </when>
          <otherwise >
            ID_TYPE = #{ID_TYPE},
          </otherwise>
        </choose>
      </if>
      <if test="NATION_CODE != null" >
        <choose >
          <when test="NATION_CODE == emptyBigDecimalValue" >
            NATION_CODE = NULL ,
          </when>
          <otherwise >
            NATION_CODE = #{NATION_CODE},
          </otherwise>
        </choose>
      </if>
      <if test="DATE_BIRTH != null" >
        DATE_BIRTH = #{DATE_BIRTH},
      </if>
      <if test="TEL_NO != null" >
        TEL_NO = #{TEL_NO},
      </if>
      <if test="POBOX_AREA != null" >
        <choose >
          <when test="POBOX_AREA == emptyBigDecimalValue" >
            POBOX_AREA = NULL ,
          </when>
          <otherwise >
            POBOX_AREA = #{POBOX_AREA},
          </otherwise>
        </choose>
      </if>
      <if test="PO_BOX != null" >
        PO_BOX = #{PO_BOX},
      </if>
      <if test="OCCUP_POSITION != null" >
        <choose >
          <when test="OCCUP_POSITION == emptyBigDecimalValue" >
            OCCUP_POSITION = NULL ,
          </when>
          <otherwise >
            OCCUP_POSITION = #{OCCUP_POSITION},
          </otherwise>
        </choose>
      </if>
      <if test="DEPT != null" >
        <choose >
          <when test="DEPT == emptyBigDecimalValue" >
            DEPT = NULL ,
          </when>
          <otherwise >
            DEPT = #{DEPT},
          </otherwise>
        </choose>
      </if>
      <if test="EMPL_DURATION != null" >
        <choose >
          <when test="EMPL_DURATION == emptyBigDecimalValue" >
            EMPL_DURATION = NULL ,
          </when>
          <otherwise >
            EMPL_DURATION = #{EMPL_DURATION},
          </otherwise>
        </choose>
      </if>
      <if test="EMP_TEL != null" >
        EMP_TEL = #{EMP_TEL},
      </if>
      <if test="MONTHLY_SALARY != null" >
        <choose >
          <when test="MONTHLY_SALARY == emptyBigDecimalValue" >
            MONTHLY_SALARY = NULL ,
          </when>
          <otherwise >
            MONTHLY_SALARY = #{MONTHLY_SALARY},
          </otherwise>
        </choose>
      </if>
      <if test="EDUC_LEVEL != null" >
        <choose >
          <when test="EDUC_LEVEL == emptyBigDecimalValue" >
            EDUC_LEVEL = NULL ,
          </when>
          <otherwise >
            EDUC_LEVEL = #{EDUC_LEVEL},
          </otherwise>
        </choose>
      </if>
      <if test="CREDIT_TYPE != null" >
        <choose >
          <when test="CREDIT_TYPE == emptyBigDecimalValue" >
            CREDIT_TYPE = NULL ,
          </when>
          <otherwise >
            CREDIT_TYPE = #{CREDIT_TYPE},
          </otherwise>
        </choose>
      </if>
      <if test="BILLING_ACC != null" >
        <choose >
          <when test="BILLING_ACC == emptyBigDecimalValue" >
            BILLING_ACC = NULL ,
          </when>
          <otherwise >
            BILLING_ACC = #{BILLING_ACC},
          </otherwise>
        </choose>
      </if>
      <if test="BANK_NAME != null" >
        BANK_NAME = #{BANK_NAME},
      </if>
      <if test="ACCOUNT_NUMBER != null" >
        ACCOUNT_NUMBER = #{ACCOUNT_NUMBER},
      </if>
      <if test="DIVISION != null" >
        <choose >
          <when test="DIVISION == emptyBigDecimalValue" >
            DIVISION = NULL ,
          </when>
          <otherwise >
            DIVISION = #{DIVISION},
          </otherwise>
        </choose>
      </if>
      <if test="CINET_CHECKED != null" >
        CINET_CHECKED = #{CINET_CHECKED},
      </if>
      <if test="DATE_APPLIED != null" >
        DATE_APPLIED = #{DATE_APPLIED},
      </if>
      <if test="APPLIED_BY != null" >
        APPLIED_BY = #{APPLIED_BY},
      </if>
      <if test="DATE_RECOMMEND != null" >
        DATE_RECOMMEND = #{DATE_RECOMMEND},
      </if>
      <if test="RECOMMEND_BY != null" >
        RECOMMEND_BY = #{RECOMMEND_BY},
      </if>
      <if test="DATE_REJECTED != null" >
        DATE_REJECTED = #{DATE_REJECTED},
      </if>
      <if test="REJECTED_BY != null" >
        REJECTED_BY = #{REJECTED_BY},
      </if>
      <if test="DATE_REVISED != null" >
        DATE_REVISED = #{DATE_REVISED},
      </if>
      <if test="REVISED_BY != null" >
        REVISED_BY = #{REVISED_BY},
      </if>
      <if test="PAYMENT_DATE != null" >
        PAYMENT_DATE = #{PAYMENT_DATE},
      </if>
      <if test="PAYMENT_AMOUNT != null" >
        <choose >
          <when test="PAYMENT_AMOUNT == emptyBigDecimalValue" >
            PAYMENT_AMOUNT = NULL ,
          </when>
          <otherwise >
            PAYMENT_AMOUNT = #{PAYMENT_AMOUNT},
          </otherwise>
        </choose>
      </if>
      <if test="NEXT_BILLING_DATE != null" >
        NEXT_BILLING_DATE = #{NEXT_BILLING_DATE},
      </if>
      <if test="EMAIL != null" >
        EMAIL = #{EMAIL},
      </if>
      <if test="LIEN_ACC != null" >
        LIEN_ACC = #{LIEN_ACC},
      </if>
      <if test="OUTSTANDING_BALANCE != null" >
        <choose >
          <when test="OUTSTANDING_BALANCE == emptyBigDecimalValue" >
            OUTSTANDING_BALANCE = NULL ,
          </when>
          <otherwise >
            OUTSTANDING_BALANCE = #{OUTSTANDING_BALANCE},
          </otherwise>
        </choose>
      </if>
      <if test="LAST_LIMIT_INCREASE != null" >
        <choose >
          <when test="LAST_LIMIT_INCREASE == emptyBigDecimalValue" >
            LAST_LIMIT_INCREASE = NULL ,
          </when>
          <otherwise >
            LAST_LIMIT_INCREASE = #{LAST_LIMIT_INCREASE},
          </otherwise>
        </choose>
      </if>
      <if test="MAILING_REGION != null" >
        <choose >
          <when test="MAILING_REGION == emptyBigDecimalValue" >
            MAILING_REGION = NULL ,
          </when>
          <otherwise >
            MAILING_REGION = #{MAILING_REGION},
          </otherwise>
        </choose>
      </if>
      <if test="MAILING_ADDRESS1 != null" >
        MAILING_ADDRESS1 = #{MAILING_ADDRESS1},
      </if>
      <if test="MAILING_ADDRESS2 != null" >
        MAILING_ADDRESS2 = #{MAILING_ADDRESS2},
      </if>
      <if test="MAILING_ADDRESS3 != null" >
        MAILING_ADDRESS3 = #{MAILING_ADDRESS3},
      </if>
      <if test="MAILING_ADDRESS4 != null" >
        MAILING_ADDRESS4 = #{MAILING_ADDRESS4},
      </if>
      <if test="MAILING_CITY != null" >
        MAILING_CITY = #{MAILING_CITY},
      </if>
      <if test="MAILING_COUNTRY != null" >
        <choose >
          <when test="MAILING_COUNTRY == emptyBigDecimalValue" >
            MAILING_COUNTRY = NULL ,
          </when>
          <otherwise >
            MAILING_COUNTRY = #{MAILING_COUNTRY},
          </otherwise>
        </choose>
      </if>
      <if test="MAILING_POBOX_AREA != null" >
        <choose >
          <when test="MAILING_POBOX_AREA == emptyBigDecimalValue" >
            MAILING_POBOX_AREA = NULL ,
          </when>
          <otherwise >
            MAILING_POBOX_AREA = #{MAILING_POBOX_AREA},
          </otherwise>
        </choose>
      </if>
      <if test="MAILING_PO_BOX != null" >
        MAILING_PO_BOX = #{MAILING_PO_BOX},
      </if>
      <if test="NO_OF_CARDS != null" >
        <choose >
          <when test="NO_OF_CARDS == emptyBigDecimalValue" >
            NO_OF_CARDS = NULL ,
          </when>
          <otherwise >
            NO_OF_CARDS = #{NO_OF_CARDS},
          </otherwise>
        </choose>
      </if>
      <if test="IS_RENEWED != null" >
        IS_RENEWED = #{IS_RENEWED},
      </if>
      <if test="EMPLOYER_NAME != null" >
        EMPLOYER_NAME = #{EMPLOYER_NAME},
      </if>
      <if test="REMAINING_AMOUNT != null" >
        <choose >
          <when test="REMAINING_AMOUNT == emptyBigDecimalValue" >
            REMAINING_AMOUNT = NULL ,
          </when>
          <otherwise >
            REMAINING_AMOUNT = #{REMAINING_AMOUNT},
          </otherwise>
        </choose>
      </if>
      <if test="TOTAL_LIMIT != null" >
        <choose >
          <when test="TOTAL_LIMIT == emptyBigDecimalValue" >
            TOTAL_LIMIT = NULL ,
          </when>
          <otherwise >
            TOTAL_LIMIT = #{TOTAL_LIMIT},
          </otherwise>
        </choose>
      </if>
      <if test="SEXE != null" >
        SEXE = #{SEXE},
      </if>
      <if test="DATE_MODIFIED_1 != null" >
        DATE_MODIFIED_1 = #{DATE_MODIFIED_1},
      </if>
      <if test="MODIFIED_BY_1 != null" >
        MODIFIED_BY_1 = #{MODIFIED_BY_1},
      </if>
      <if test="APP_REF != null" >
        <choose >
          <when test="APP_REF == emptyBigDecimalValue" >
            APP_REF = NULL ,
          </when>
          <otherwise >
            APP_REF = #{APP_REF},
          </otherwise>
        </choose>
      </if>
      <if test="LIMIT_BASED_ON != null" >
        LIMIT_BASED_ON = #{LIMIT_BASED_ON},
      </if>
      <if test="LIMIT_CHECK_PERIOD != null" >
        LIMIT_CHECK_PERIOD = #{LIMIT_CHECK_PERIOD},
      </if>
      <if test="POS_LIMIT_BASED_ON != null" >
        POS_LIMIT_BASED_ON = #{POS_LIMIT_BASED_ON},
      </if>
      <if test="POS_LIMIT_CHECK_PERIOD != null" >
        POS_LIMIT_CHECK_PERIOD = #{POS_LIMIT_CHECK_PERIOD},
      </if>
      <if test="POS_LIMIT_AMOUNT != null" >
        <choose >
          <when test="POS_LIMIT_AMOUNT == emptyBigDecimalValue" >
            POS_LIMIT_AMOUNT = NULL ,
          </when>
          <otherwise >
            POS_LIMIT_AMOUNT = #{POS_LIMIT_AMOUNT},
          </otherwise>
        </choose>
      </if>
      <if test="SENT_TO_PROV_BY != null" >
        SENT_TO_PROV_BY = #{SENT_TO_PROV_BY},
      </if>
      <if test="DATE_SENT_TO_PROV != null" >
        DATE_SENT_TO_PROV = #{DATE_SENT_TO_PROV},
      </if>
      <if test="RECEIVED_FROM_PROV_BY != null" >
        RECEIVED_FROM_PROV_BY = #{RECEIVED_FROM_PROV_BY},
      </if>
      <if test="DATE_RECEIVED_FROM_PROV != null" >
        DATE_RECEIVED_FROM_PROV = #{DATE_RECEIVED_FROM_PROV},
      </if>
      <if test="RECEIVED_BY_BRANCH_BY != null" >
        RECEIVED_BY_BRANCH_BY = #{RECEIVED_BY_BRANCH_BY},
      </if>
      <if test="DATE_RECEIVED_BY_BRANCH != null" >
        DATE_RECEIVED_BY_BRANCH = #{DATE_RECEIVED_BY_BRANCH},
      </if>
      <if test="ISSUED_INIT != null" >
        ISSUED_INIT = #{ISSUED_INIT},
      </if>
      <if test="DATE_ISSUED_INIT != null" >
        DATE_ISSUED_INIT = #{DATE_ISSUED_INIT},
      </if>
      <if test="ACTIVATED_INIT != null" >
        ACTIVATED_INIT = #{ACTIVATED_INIT},
      </if>
      <if test="DATE_ACTIVATED_INIT != null" >
        DATE_ACTIVATED_INIT = #{DATE_ACTIVATED_INIT},
      </if>
      <if test="MONITORED_INIT != null" >
        MONITORED_INIT = #{MONITORED_INIT},
      </if>
      <if test="DATE_MONITORED_INIT != null" >
        DATE_MONITORED_INIT = #{DATE_MONITORED_INIT},
      </if>
      <if test="DEACTIVATED_INIT != null" >
        DEACTIVATED_INIT = #{DEACTIVATED_INIT},
      </if>
      <if test="DATE_DEACTIVATED_INIT != null" >
        DATE_DEACTIVATED_INIT = #{DATE_DEACTIVATED_INIT},
      </if>
      <if test="DESTROYED_INIT != null" >
        DESTROYED_INIT = #{DESTROYED_INIT},
      </if>
      <if test="DATE_DESTROYED_INIT != null" >
        DATE_DESTROYED_INIT = #{DATE_DESTROYED_INIT},
      </if>
      <if test="REPLACED_INIT != null" >
        REPLACED_INIT = #{REPLACED_INIT},
      </if>
      <if test="DATE_REPLACED_INIT != null" >
        DATE_REPLACED_INIT = #{DATE_REPLACED_INIT},
      </if>
      <if test="CANCELLED_INIT != null" >
        CANCELLED_INIT = #{CANCELLED_INIT},
      </if>
      <if test="DATE_CANCELLED_INIT != null" >
        DATE_CANCELLED_INIT = #{DATE_CANCELLED_INIT},
      </if>
      <if test="BLOCKED_INIT != null" >
        BLOCKED_INIT = #{BLOCKED_INIT},
      </if>
      <if test="DATE_BLOCKED_INIT != null" >
        DATE_BLOCKED_INIT = #{DATE_BLOCKED_INIT},
      </if>
      <if test="UNBLOCKED_INIT != null" >
        UNBLOCKED_INIT = #{UNBLOCKED_INIT},
      </if>
      <if test="DATE_UNBLOCKED_INIT != null" >
        DATE_UNBLOCKED_INIT = #{DATE_UNBLOCKED_INIT},
      </if>
      <if test="HEATED_INIT != null" >
        HEATED_INIT = #{HEATED_INIT},
      </if>
      <if test="DATE_HEATED_INIT != null" >
        DATE_HEATED_INIT = #{DATE_HEATED_INIT},
      </if>
      <if test="RENEW_INIT != null" >
        RENEW_INIT = #{RENEW_INIT},
      </if>
      <if test="DATE_RENEW_INIT != null" >
        DATE_RENEW_INIT = #{DATE_RENEW_INIT},
      </if>
      <if test="RELATED_TO_BR != null" >
        <choose >
          <when test="RELATED_TO_BR == emptyBigDecimalValue" >
            RELATED_TO_BR = NULL ,
          </when>
          <otherwise >
            RELATED_TO_BR = #{RELATED_TO_BR},
          </otherwise>
        </choose>
      </if>
      <if test="POSTAL_CODE1 != null" >
        POSTAL_CODE1 = #{POSTAL_CODE1},
      </if>
      <if test="MAILING_POSTAL_CODE1 != null" >
        MAILING_POSTAL_CODE1 = #{MAILING_POSTAL_CODE1},
      </if>
      <if test="POSTAL_CODE != null" >
        <choose >
          <when test="POSTAL_CODE == emptyBigDecimalValue" >
            POSTAL_CODE = NULL ,
          </when>
          <otherwise >
            POSTAL_CODE = #{POSTAL_CODE},
          </otherwise>
        </choose>
      </if>
      <if test="MAILING_POSTAL_CODE != null" >
        <choose >
          <when test="MAILING_POSTAL_CODE == emptyBigDecimalValue" >
            MAILING_POSTAL_CODE = NULL ,
          </when>
          <otherwise >
            MAILING_POSTAL_CODE = #{MAILING_POSTAL_CODE},
          </otherwise>
        </choose>
      </if>
      <if test="REEDIT_PIN != null" >
        REEDIT_PIN = #{REEDIT_PIN},
      </if>
      <if test="REEDIT_PIN_DATE != null" >
        REEDIT_PIN_DATE = #{REEDIT_PIN_DATE},
      </if>
      <if test="PARENT_CARD != null" >
        PARENT_CARD = #{PARENT_CARD},
      </if>
      <if test="PARENT_APP_REF != null" >
        <choose >
          <when test="PARENT_APP_REF == emptyBigDecimalValue" >
            PARENT_APP_REF = NULL ,
          </when>
          <otherwise >
            PARENT_APP_REF = #{PARENT_APP_REF},
          </otherwise>
        </choose>
      </if>
      <if test="ACTION != null" >
        ACTION = #{ACTION},
      </if>
      <if test="CARD_ALERT_STATUS != null" >
        CARD_ALERT_STATUS = #{CARD_ALERT_STATUS},
      </if>
      <if test="ORIGINAL_CARD_NO != null" >
        ORIGINAL_CARD_NO = #{ORIGINAL_CARD_NO},
      </if>
      <if test="BATCH_NO1 != null" >
        BATCH_NO1 = #{BATCH_NO1},
      </if>
      <if test="PURCHASER_ID_TYPE != null" >
        <choose >
          <when test="PURCHASER_ID_TYPE == emptyBigDecimalValue" >
            PURCHASER_ID_TYPE = NULL ,
          </when>
          <otherwise >
            PURCHASER_ID_TYPE = #{PURCHASER_ID_TYPE},
          </otherwise>
        </choose>
      </if>
      <if test="RECEIVER_ID_TYPE != null" >
        <choose >
          <when test="RECEIVER_ID_TYPE == emptyBigDecimalValue" >
            RECEIVER_ID_TYPE = NULL ,
          </when>
          <otherwise >
            RECEIVER_ID_TYPE = #{RECEIVER_ID_TYPE},
          </otherwise>
        </choose>
      </if>
      <if test="RELATED_TO != null" >
        <choose >
          <when test="RELATED_TO == emptyBigDecimalValue" >
            RELATED_TO = NULL ,
          </when>
          <otherwise >
            RELATED_TO = #{RELATED_TO},
          </otherwise>
        </choose>
      </if>
      <if test="ADDRESS_1 != null" >
        ADDRESS_1 = #{ADDRESS_1},
      </if>
      <if test="ADDRESS_2 != null" >
        ADDRESS_2 = #{ADDRESS_2},
      </if>
      <if test="ADDRESS_3 != null" >
        ADDRESS_3 = #{ADDRESS_3},
      </if>
      <if test="COUNTRY != null" >
        COUNTRY = #{COUNTRY},
      </if>
      <if test="NO_LIABILITY != null" >
        NO_LIABILITY = #{NO_LIABILITY},
      </if>
      <if test="REPLACE_REISSUE != null" >
        REPLACE_REISSUE = #{REPLACE_REISSUE},
      </if>
      <if test="APPLY_REASON != null" >
        APPLY_REASON = #{APPLY_REASON},
      </if>
      <if test="CIF_HOLDER != null" >
        <choose >
          <when test="CIF_HOLDER == emptyBigDecimalValue" >
            CIF_HOLDER = NULL ,
          </when>
          <otherwise >
            CIF_HOLDER = #{CIF_HOLDER},
          </otherwise>
        </choose>
      </if>
      <if test="COUNTRY_CODE != null" >
        <choose >
          <when test="COUNTRY_CODE == emptyBigDecimalValue" >
            COUNTRY_CODE = NULL ,
          </when>
          <otherwise >
            COUNTRY_CODE = #{COUNTRY_CODE},
          </otherwise>
        </choose>
      </if>
      <if test="HOLD_FOR_RENEWAL != null" >
        HOLD_FOR_RENEWAL = #{HOLD_FOR_RENEWAL},
      </if>
      <if test="MAX_BAL != null" >
        <choose >
          <when test="MAX_BAL == emptyBigDecimalValue" >
            MAX_BAL = NULL ,
          </when>
          <otherwise >
            MAX_BAL = #{MAX_BAL},
          </otherwise>
        </choose>
      </if>
      <if test="PREV_EXP_DATE != null" >
        PREV_EXP_DATE = #{PREV_EXP_DATE},
      </if>
      <if test="PREV_STATUS != null" >
        PREV_STATUS = #{PREV_STATUS},
      </if>
      <if test="SOURCE_INCOME != null" >
        SOURCE_INCOME = #{SOURCE_INCOME},
      </if>
      <if test="CARD_MESSAGE != null" >
        <choose >
          <when test="CARD_MESSAGE == emptyBigDecimalValue" >
            CARD_MESSAGE = NULL ,
          </when>
          <otherwise >
            CARD_MESSAGE = #{CARD_MESSAGE},
          </otherwise>
        </choose>
      </if>
      <if test="DESIGN != null" >
        <choose >
          <when test="DESIGN == emptyBigDecimalValue" >
            DESIGN = NULL ,
          </when>
          <otherwise >
            DESIGN = #{DESIGN},
          </otherwise>
        </choose>
      </if>
      <if test="MESSAGE_INFO != null" >
        MESSAGE_INFO = #{MESSAGE_INFO},
      </if>
      <if test="PURCHASER_EMAIL != null" >
        PURCHASER_EMAIL = #{PURCHASER_EMAIL},
      </if>
      <if test="PURCHASER_ID_NO != null" >
        PURCHASER_ID_NO = #{PURCHASER_ID_NO},
      </if>
      <if test="PURCHASER_NAME != null" >
        PURCHASER_NAME = #{PURCHASER_NAME},
      </if>
      <if test="PURCHASER_PHONE != null" >
        PURCHASER_PHONE = #{PURCHASER_PHONE},
      </if>
      <if test="RECEIVER_EMAIL != null" >
        RECEIVER_EMAIL = #{RECEIVER_EMAIL},
      </if>
      <if test="RECEIVER_ID_NO != null" >
        RECEIVER_ID_NO = #{RECEIVER_ID_NO},
      </if>
      <if test="RECEIVER_NAME != null" >
        RECEIVER_NAME = #{RECEIVER_NAME},
      </if>
      <if test="RECEIVER_PHONE != null" >
        RECEIVER_PHONE = #{RECEIVER_PHONE},
      </if>
      <if test="BIOMETRIC_APPROVED_YN != null" >
        BIOMETRIC_APPROVED_YN = #{BIOMETRIC_APPROVED_YN},
      </if>
       <if test="CARD_READER_SRL != null" >
        CARD_READER_SRL = #{CARD_READER_SRL},
      </if>
    </set>
    where APPLICATION_ID = #{APPLICATION_ID}
      and BRANCH_CODE = #{BRANCH_CODE}
      and COMP_CODE = #{COMP_CODE}
  </sql>
  <update id="updateCTSCARDS_MGT_ALERT" parameterType="com.path.dbmaps.vo.CTSCARDS_MGT_ALERTVO" >
    <include refid="sql_updateCTSCARDS_MGT_ALERT" />
  </update>
</mapper>