<?xml version="1.0" encoding="UTF-8" ?>
<!DOCTYPE mapper PUBLIC "-//mybatis.org//DTD Mapper 3.0//EN" "http://mybatis.org/dtd/mybatis-3-mapper.dtd" >
<mapper namespace="FASAST" >
  <resultMap id="BaseResultMap" type="com.path.dbmaps.vo.FASASTVO" >
    <id column="CATEGORY_CODE" property="CATEGORY_CODE" />
    <id column="CLASS_CODE" property="CLASS_CODE" />
    <id column="CODE" property="CODE" />
    <id column="COMP_CODE" property="COMP_CODE" />
    <result column="STATUS" property="STATUS" />
    <result column="REFERENCE" property="REFERENCE" />
    <result column="LEASE_VALUE" property="LEASE_VALUE" />
    <result column="USEFUL_LIFE" property="USEFUL_LIFE" />
    <result column="UTILIZED_PERIOD" property="UTILIZED_PERIOD" />
    <result column="REMAINING_LIFE" property="REMAINING_LIFE" />
    <result column="LOCATION" property="LOCATION" />
    <result column="ASSIGNED_TO" property="ASSIGNED_TO" />
    <result column="DATE_ASSIGNED" property="DATE_ASSIGNED" />
    <result column="FIELD1" property="FIELD1" />
    <result column="FIELD2" property="FIELD2" />
    <result column="FIELD3" property="FIELD3" />
    <result column="FIELD4" property="FIELD4" />
    <result column="ACQUISITION_VALUE" property="ACQUISITION_VALUE" />
    <result column="CAPITALIZED_VALUE" property="CAPITALIZED_VALUE" />
    <result column="ACCUMULATED_DEPRECIATION_VALUE" property="ACCUMULATED_DEPRECIATION_VALUE" />
    <result column="CAPITALIZED_ADDITIONS_VALUE" property="CAPITALIZED_ADDITIONS_VALUE" />
    <result column="LATEST_MARKET_VALUE" property="LATEST_MARKET_VALUE" />
    <result column="LATEST_MARKET_DATE" property="LATEST_MARKET_DATE" />
    <result column="DEPRECIATION_RATE" property="DEPRECIATION_RATE" />
    <result column="DATE_ACQUIRED" property="DATE_ACQUIRED" />
    <result column="ACQUIRED_BY" property="ACQUIRED_BY" />
    <result column="DATE_CAPITALIZED" property="DATE_CAPITALIZED" />
    <result column="CAPITALIZED_BY" property="CAPITALIZED_BY" />
    <result column="DATE_SUSPENDED" property="DATE_SUSPENDED" />
    <result column="SUSPENDED_BY" property="SUSPENDED_BY" />
    <result column="DATE_RETIRED" property="DATE_RETIRED" />
    <result column="RETIRED_BY" property="RETIRED_BY" />
    <result column="DATE_REINSTATED" property="DATE_REINSTATED" />
    <result column="REINSTATED_BY" property="REINSTATED_BY" />
    <result column="DATE_SOLD" property="DATE_SOLD" />
    <result column="SOLD_BY" property="SOLD_BY" />
    <result column="DATE_REACTIVATED" property="DATE_REACTIVATED" />
    <result column="REACTIVATED_BY" property="REACTIVATED_BY" />
    <result column="STATUS_TMP" property="STATUS_TMP" />
    <result column="STATUS_TRX" property="STATUS_TRX" />
    <result column="LAST_MAINTENANCE_DATE" property="LAST_MAINTENANCE_DATE" />
    <result column="OWNED_LEASED" property="OWNED_LEASED" />
    <result column="SALVAGE_VALUE" property="SALVAGE_VALUE" />
    <result column="TRX_DIV_CODE" property="TRX_DIV_CODE" />
    <result column="TRX_DEPT_CODE" property="TRX_DEPT_CODE" />
    <result column="TRX_TYPE" property="TRX_TYPE" />
    <result column="TRX_NBR" property="TRX_NBR" />
    <result column="APPROVED_TRX_DIV_CODE" property="APPROVED_TRX_DIV_CODE" />
    <result column="APPROVED_TRX_DEPT_CODE" property="APPROVED_TRX_DEPT_CODE" />
    <result column="APPROVED_TRX_TYPE" property="APPROVED_TRX_TYPE" />
    <result column="APPROVED_TRX_NBR" property="APPROVED_TRX_NBR" />
    <result column="DEPRECIATION_STATUS" property="DEPRECIATION_STATUS" />
    <result column="VALUE_TO_DEPRECIATE" property="VALUE_TO_DEPRECIATE" />
    <result column="LIFE_TO_DEPRECIATE" property="LIFE_TO_DEPRECIATE" />
    <result column="OLD_CAPITALIZED_VALUE" property="OLD_CAPITALIZED_VALUE" />
    <result column="OLD_USEFUL_LIFE" property="OLD_USEFUL_LIFE" />
    <result column="LAST_DEPRECIATION_DATE" property="LAST_DEPRECIATION_DATE" />
    <result column="OLD_DEPRECIATION_METHOD" property="OLD_DEPRECIATION_METHOD" />
    <result column="CAPITALIZATION_USEFUL_LIFE" property="CAPITALIZATION_USEFUL_LIFE" />
    <result column="USEFUL_LIFE_FROM" property="USEFUL_LIFE_FROM" />
    <result column="VIA_TRX_TYPE" property="VIA_TRX_TYPE" />
    <result column="PURCHASE_AMOUNT" property="PURCHASE_AMOUNT" />
    <result column="PURCHASE_CY_CODE" property="PURCHASE_CY_CODE" />
    <result column="PURCHASE_CY_RATE" property="PURCHASE_CY_RATE" />
    <result column="PURCHASE_CY_UNIT" property="PURCHASE_CY_UNIT" />
    <result column="PURCHASE_CY_MULT_DIV" property="PURCHASE_CY_MULT_DIV" />
    <result column="SUPP_CODE" property="SUPP_CODE" />
    <result column="BRANCH_CODE" property="BRANCH_CODE" />
    <result column="RETIRE_FR_SL" property="RETIRE_FR_SL" />
    <result column="VIA_TRX_NBR" property="VIA_TRX_NBR" />
    <result column="BARCODE" property="BARCODE" />
    <result column="UNIT_PRICE" property="UNIT_PRICE" />
    <result column="QTY" property="QTY" />
    <result column="ASSET_TYPE" property="ASSET_TYPE" />
    <result column="ACQ_CY_CODE" property="ACQ_CY_CODE" />
    <result column="ACQ_CY_RATE" property="ACQ_CY_RATE" />
    <result column="ACQ_CY_MULT_DIV" property="ACQ_CY_MULT_DIV" />
    <result column="ACQ_CV_VALUE" property="ACQ_CV_VALUE" />
    <result column="FIELD5" property="FIELD5" />
    <result column="FIELD6" property="FIELD6" />
    <result column="OLD_CAPITALIZED_ADD_VALUE" property="OLD_CAPITALIZED_ADD_VALUE" />
    <result column="OLD_UTILIZED_PERIOD" property="OLD_UTILIZED_PERIOD" />
    <result column="LEASED_FROM_DATE" property="LEASED_FROM_DATE" />
    <result column="LEASED_TO_DATE" property="LEASED_TO_DATE" />
    <result column="MANUFACTURER_SL_NO" property="MANUFACTURER_SL_NO" />
    <result column="LOSS_ON_REVAL" property="LOSS_ON_REVAL" />
    <result column="REVAL_RESERVE" property="REVAL_RESERVE" />
    <result column="ANNUAL_DEPREC_RATE" property="ANNUAL_DEPREC_RATE" />
    <result column="DEPRECIATION_BASIS" property="DEPRECIATION_BASIS" />
    <result column="EMP_CODE" property="EMP_CODE" />
    <result column="BARCODE_TYPE" property="BARCODE_TYPE" />
    <result column="TAX_AMOUNT" property="TAX_AMOUNT" />
    <result column="FIELD10" property="FIELD10" />
    <result column="FIELD11" property="FIELD11" />
    <result column="FIELD12" property="FIELD12" />
    <result column="FIELD7" property="FIELD7" />
    <result column="FIELD8" property="FIELD8" />
    <result column="FIELD9" property="FIELD9" />
    <result column="LATEST_MARKET_VALUE_FOR_PROV" property="LATEST_MARKET_VALUE_FOR_PROV" />
    <result column="FACILITY_BRANCH" property="FACILITY_BRANCH" />
    <result column="FACILITY_NO" property="FACILITY_NO" />
    <result column="SUBLIMIT_NO" property="SUBLIMIT_NO" />
    <result column="TAX_ANNUAL_DEPRECIATION_RATE" property="TAX_ANNUAL_DEPRECIATION_RATE" />
    <result column="TAX_DEFAULT_USEFUL_LIFE" property="TAX_DEFAULT_USEFUL_LIFE" />
    <result column="TAX_DEPRECIATION_BASIS" property="TAX_DEPRECIATION_BASIS" />
    <result column="TAX_DEPRECIATION_METHOD" property="TAX_DEPRECIATION_METHOD" />
    <result column="TAX_INIT_ALLOWANCE_PERC" property="TAX_INIT_ALLOWANCE_PERC" />
    <result column="LAST_TAX_DEPRECIATION_DATE" property="LAST_TAX_DEPRECIATION_DATE" />
    <result column="TAX_ACCUMU_DEPRECIATION_VALUE" property="TAX_ACCUMU_DEPRECIATION_VALUE" />
    <result column="TAX_DEPRECIATION_RATE" property="TAX_DEPRECIATION_RATE" />
    <result column="TAX_REMAINING_LIFE" property="TAX_REMAINING_LIFE" />
    <result column="TAX_USEFUL_LIFE" property="TAX_USEFUL_LIFE" />
    <result column="TAX_UTILIZED_PERIOD" property="TAX_UTILIZED_PERIOD" />
    <result column="ASSET_CY_CODE" property="ASSET_CY_CODE" />
    <result column="APPROVED_BY" property="APPROVED_BY" />
    <result column="DATE_APPROVED" property="DATE_APPROVED" />
    <result column="DATE_MODIFIED" property="DATE_MODIFIED" />
    <result column="MODIFIED_BY" property="MODIFIED_BY" />
    <result column="SERVER_APPROVED_DATE" property="SERVER_APPROVED_DATE" />
    <result column="SERVER_MODIFIED_DATE" property="SERVER_MODIFIED_DATE" />
    <result column="FACILITY_ASSET_LINE_NO" property="FACILITY_ASSET_LINE_NO" />
    <result column="DATE_UPDATED" property="DATE_UPDATED" />
    <result column="VENDOR_DOWN_PAYMENT" property="VENDOR_DOWN_PAYMENT" />
    <result column="SUB_STATUS" property="SUB_STATUS" />
    <result column="ASSET_SUB_STATUS" property="ASSET_SUB_STATUS" />
    <result column="DOWN_PAYMENT_AMOUNT" property="DOWN_PAYMENT_AMOUNT" />
  </resultMap>
  <sql id="Base_Column_List" >
    CATEGORY_CODE, CLASS_CODE, CODE, COMP_CODE, STATUS, REFERENCE, LEASE_VALUE, USEFUL_LIFE, 
    UTILIZED_PERIOD, REMAINING_LIFE, LOCATION, ASSIGNED_TO, DATE_ASSIGNED, FIELD1, FIELD2, 
    FIELD3, FIELD4, ACQUISITION_VALUE, CAPITALIZED_VALUE, ACCUMULATED_DEPRECIATION_VALUE, 
    CAPITALIZED_ADDITIONS_VALUE, LATEST_MARKET_VALUE, LATEST_MARKET_DATE, DEPRECIATION_RATE, 
    DATE_ACQUIRED, ACQUIRED_BY, DATE_CAPITALIZED, CAPITALIZED_BY, DATE_SUSPENDED, SUSPENDED_BY, 
    DATE_RETIRED, RETIRED_BY, DATE_REINSTATED, REINSTATED_BY, DATE_SOLD, SOLD_BY, DATE_REACTIVATED, 
    REACTIVATED_BY, STATUS_TMP, STATUS_TRX, LAST_MAINTENANCE_DATE, OWNED_LEASED, SALVAGE_VALUE, 
    TRX_DIV_CODE, TRX_DEPT_CODE, TRX_TYPE, TRX_NBR, APPROVED_TRX_DIV_CODE, APPROVED_TRX_DEPT_CODE, 
    APPROVED_TRX_TYPE, APPROVED_TRX_NBR, DEPRECIATION_STATUS, VALUE_TO_DEPRECIATE, LIFE_TO_DEPRECIATE, 
    OLD_CAPITALIZED_VALUE, OLD_USEFUL_LIFE, LAST_DEPRECIATION_DATE, OLD_DEPRECIATION_METHOD, 
    CAPITALIZATION_USEFUL_LIFE, USEFUL_LIFE_FROM, VIA_TRX_TYPE, PURCHASE_AMOUNT, PURCHASE_CY_CODE, 
    PURCHASE_CY_RATE, PURCHASE_CY_UNIT, PURCHASE_CY_MULT_DIV, SUPP_CODE, BRANCH_CODE, 
    RETIRE_FR_SL, VIA_TRX_NBR, BARCODE, UNIT_PRICE, QTY, ASSET_TYPE, ACQ_CY_CODE, ACQ_CY_RATE, 
    ACQ_CY_MULT_DIV, ACQ_CV_VALUE, FIELD5, FIELD6, OLD_CAPITALIZED_ADD_VALUE, OLD_UTILIZED_PERIOD, 
    LEASED_FROM_DATE, LEASED_TO_DATE, MANUFACTURER_SL_NO, LOSS_ON_REVAL, REVAL_RESERVE, 
    ANNUAL_DEPREC_RATE, DEPRECIATION_BASIS, EMP_CODE, BARCODE_TYPE, TAX_AMOUNT, FIELD10, 
    FIELD11, FIELD12, FIELD7, FIELD8, FIELD9, LATEST_MARKET_VALUE_FOR_PROV, FACILITY_BRANCH, 
    FACILITY_NO, SUBLIMIT_NO, TAX_ANNUAL_DEPRECIATION_RATE, TAX_DEFAULT_USEFUL_LIFE, 
    TAX_DEPRECIATION_BASIS, TAX_DEPRECIATION_METHOD, TAX_INIT_ALLOWANCE_PERC, LAST_TAX_DEPRECIATION_DATE, 
    TAX_ACCUMU_DEPRECIATION_VALUE, TAX_DEPRECIATION_RATE, TAX_REMAINING_LIFE, TAX_USEFUL_LIFE, 
    TAX_UTILIZED_PERIOD, ASSET_CY_CODE, APPROVED_BY, DATE_APPROVED, DATE_MODIFIED, MODIFIED_BY, 
    SERVER_APPROVED_DATE, SERVER_MODIFIED_DATE, FACILITY_ASSET_LINE_NO, DATE_UPDATED, 
    VENDOR_DOWN_PAYMENT, SUB_STATUS, ASSET_SUB_STATUS, DOWN_PAYMENT_AMOUNT
  </sql>
  <select id="selectFASAST" resultMap="BaseResultMap" parameterType="com.path.dbmaps.vo.FASASTVOKey" >
    select 
    <include refid="Base_Column_List" />
    from FASAST
    where CATEGORY_CODE = #{CATEGORY_CODE}
      and CLASS_CODE = #{CLASS_CODE}
      and CODE = #{CODE}
      and COMP_CODE = #{COMP_CODE}
  </select>
  <delete id="deleteFASAST" parameterType="com.path.dbmaps.vo.FASASTVOKey" >
    delete from FASAST
    where CATEGORY_CODE = #{CATEGORY_CODE}
      and CLASS_CODE = #{CLASS_CODE}
      and CODE = #{CODE}
      and COMP_CODE = #{COMP_CODE}
  </delete>
  <insert id="insertFASAST" parameterType="com.path.dbmaps.vo.FASASTVO" >
    insert into FASAST
    <trim prefix="(" suffix=")" suffixOverrides="," >
      <if test="CATEGORY_CODE != null and CATEGORY_CODE != emptyBigDecimalValue" >
        CATEGORY_CODE,
      </if>
      <if test="CLASS_CODE != null and CLASS_CODE != emptyBigDecimalValue" >
        CLASS_CODE,
      </if>
      <if test="CODE != null and CODE != emptyBigDecimalValue" >
        CODE,
      </if>
      <if test="COMP_CODE != null and COMP_CODE != emptyBigDecimalValue" >
        COMP_CODE,
      </if>
      <if test="STATUS != null and STATUS != emptyBigDecimalValue" >
        STATUS,
      </if>
      <if test="REFERENCE != null and !&quot;&quot;.equals(REFERENCE)" >
        REFERENCE,
      </if>
      <if test="LEASE_VALUE != null and LEASE_VALUE != emptyBigDecimalValue" >
        LEASE_VALUE,
      </if>
      <if test="USEFUL_LIFE != null and USEFUL_LIFE != emptyBigDecimalValue" >
        USEFUL_LIFE,
      </if>
      <if test="UTILIZED_PERIOD != null and UTILIZED_PERIOD != emptyBigDecimalValue" >
        UTILIZED_PERIOD,
      </if>
      <if test="REMAINING_LIFE != null and REMAINING_LIFE != emptyBigDecimalValue" >
        REMAINING_LIFE,
      </if>
      <if test="LOCATION != null and LOCATION != emptyBigDecimalValue" >
        LOCATION,
      </if>
      <if test="ASSIGNED_TO != null and !&quot;&quot;.equals(ASSIGNED_TO)" >
        ASSIGNED_TO,
      </if>
      <if test="DATE_ASSIGNED != null" >
        DATE_ASSIGNED,
      </if>
      <if test="FIELD1 != null and !&quot;&quot;.equals(FIELD1)" >
        FIELD1,
      </if>
      <if test="FIELD2 != null and !&quot;&quot;.equals(FIELD2)" >
        FIELD2,
      </if>
      <if test="FIELD3 != null and !&quot;&quot;.equals(FIELD3)" >
        FIELD3,
      </if>
      <if test="FIELD4 != null and !&quot;&quot;.equals(FIELD4)" >
        FIELD4,
      </if>
      <if test="ACQUISITION_VALUE != null and ACQUISITION_VALUE != emptyBigDecimalValue" >
        ACQUISITION_VALUE,
      </if>
      <if test="CAPITALIZED_VALUE != null and CAPITALIZED_VALUE != emptyBigDecimalValue" >
        CAPITALIZED_VALUE,
      </if>
      <if test="ACCUMULATED_DEPRECIATION_VALUE != null and ACCUMULATED_DEPRECIATION_VALUE != emptyBigDecimalValue" >
        ACCUMULATED_DEPRECIATION_VALUE,
      </if>
      <if test="CAPITALIZED_ADDITIONS_VALUE != null and CAPITALIZED_ADDITIONS_VALUE != emptyBigDecimalValue" >
        CAPITALIZED_ADDITIONS_VALUE,
      </if>
      <if test="LATEST_MARKET_VALUE != null and LATEST_MARKET_VALUE != emptyBigDecimalValue" >
        LATEST_MARKET_VALUE,
      </if>
      <if test="LATEST_MARKET_DATE != null" >
        LATEST_MARKET_DATE,
      </if>
      <if test="DEPRECIATION_RATE != null and DEPRECIATION_RATE != emptyBigDecimalValue" >
        DEPRECIATION_RATE,
      </if>
      <if test="DATE_ACQUIRED != null" >
        DATE_ACQUIRED,
      </if>
      <if test="ACQUIRED_BY != null and !&quot;&quot;.equals(ACQUIRED_BY)" >
        ACQUIRED_BY,
      </if>
      <if test="DATE_CAPITALIZED != null" >
        DATE_CAPITALIZED,
      </if>
      <if test="CAPITALIZED_BY != null and !&quot;&quot;.equals(CAPITALIZED_BY)" >
        CAPITALIZED_BY,
      </if>
      <if test="DATE_SUSPENDED != null" >
        DATE_SUSPENDED,
      </if>
      <if test="SUSPENDED_BY != null and !&quot;&quot;.equals(SUSPENDED_BY)" >
        SUSPENDED_BY,
      </if>
      <if test="DATE_RETIRED != null" >
        DATE_RETIRED,
      </if>
      <if test="RETIRED_BY != null and !&quot;&quot;.equals(RETIRED_BY)" >
        RETIRED_BY,
      </if>
      <if test="DATE_REINSTATED != null" >
        DATE_REINSTATED,
      </if>
      <if test="REINSTATED_BY != null and !&quot;&quot;.equals(REINSTATED_BY)" >
        REINSTATED_BY,
      </if>
      <if test="DATE_SOLD != null" >
        DATE_SOLD,
      </if>
      <if test="SOLD_BY != null and !&quot;&quot;.equals(SOLD_BY)" >
        SOLD_BY,
      </if>
      <if test="DATE_REACTIVATED != null" >
        DATE_REACTIVATED,
      </if>
      <if test="REACTIVATED_BY != null and !&quot;&quot;.equals(REACTIVATED_BY)" >
        REACTIVATED_BY,
      </if>
      <if test="STATUS_TMP != null and STATUS_TMP != emptyBigDecimalValue" >
        STATUS_TMP,
      </if>
      <if test="STATUS_TRX != null and STATUS_TRX != emptyBigDecimalValue" >
        STATUS_TRX,
      </if>
      <if test="LAST_MAINTENANCE_DATE != null" >
        LAST_MAINTENANCE_DATE,
      </if>
      <if test="OWNED_LEASED != null and OWNED_LEASED != emptyBigDecimalValue" >
        OWNED_LEASED,
      </if>
      <if test="SALVAGE_VALUE != null and SALVAGE_VALUE != emptyBigDecimalValue" >
        SALVAGE_VALUE,
      </if>
      <if test="TRX_DIV_CODE != null and TRX_DIV_CODE != emptyBigDecimalValue" >
        TRX_DIV_CODE,
      </if>
      <if test="TRX_DEPT_CODE != null and TRX_DEPT_CODE != emptyBigDecimalValue" >
        TRX_DEPT_CODE,
      </if>
      <if test="TRX_TYPE != null and TRX_TYPE != emptyBigDecimalValue" >
        TRX_TYPE,
      </if>
      <if test="TRX_NBR != null and TRX_NBR != emptyBigDecimalValue" >
        TRX_NBR,
      </if>
      <if test="APPROVED_TRX_DIV_CODE != null and APPROVED_TRX_DIV_CODE != emptyBigDecimalValue" >
        APPROVED_TRX_DIV_CODE,
      </if>
      <if test="APPROVED_TRX_DEPT_CODE != null and APPROVED_TRX_DEPT_CODE != emptyBigDecimalValue" >
        APPROVED_TRX_DEPT_CODE,
      </if>
      <if test="APPROVED_TRX_TYPE != null and APPROVED_TRX_TYPE != emptyBigDecimalValue" >
        APPROVED_TRX_TYPE,
      </if>
      <if test="APPROVED_TRX_NBR != null and APPROVED_TRX_NBR != emptyBigDecimalValue" >
        APPROVED_TRX_NBR,
      </if>
      <if test="DEPRECIATION_STATUS != null and DEPRECIATION_STATUS != emptyBigDecimalValue" >
        DEPRECIATION_STATUS,
      </if>
      <if test="VALUE_TO_DEPRECIATE != null and !&quot;&quot;.equals(VALUE_TO_DEPRECIATE)" >
        VALUE_TO_DEPRECIATE,
      </if>
      <if test="LIFE_TO_DEPRECIATE != null and !&quot;&quot;.equals(LIFE_TO_DEPRECIATE)" >
        LIFE_TO_DEPRECIATE,
      </if>
      <if test="OLD_CAPITALIZED_VALUE != null and OLD_CAPITALIZED_VALUE != emptyBigDecimalValue" >
        OLD_CAPITALIZED_VALUE,
      </if>
      <if test="OLD_USEFUL_LIFE != null and OLD_USEFUL_LIFE != emptyBigDecimalValue" >
        OLD_USEFUL_LIFE,
      </if>
      <if test="LAST_DEPRECIATION_DATE != null" >
        LAST_DEPRECIATION_DATE,
      </if>
      <if test="OLD_DEPRECIATION_METHOD != null and OLD_DEPRECIATION_METHOD != emptyBigDecimalValue" >
        OLD_DEPRECIATION_METHOD,
      </if>
      <if test="CAPITALIZATION_USEFUL_LIFE != null and CAPITALIZATION_USEFUL_LIFE != emptyBigDecimalValue" >
        CAPITALIZATION_USEFUL_LIFE,
      </if>
      <if test="USEFUL_LIFE_FROM != null and USEFUL_LIFE_FROM != emptyBigDecimalValue" >
        USEFUL_LIFE_FROM,
      </if>
      <if test="VIA_TRX_TYPE != null and VIA_TRX_TYPE != emptyBigDecimalValue" >
        VIA_TRX_TYPE,
      </if>
      <if test="PURCHASE_AMOUNT != null and PURCHASE_AMOUNT != emptyBigDecimalValue" >
        PURCHASE_AMOUNT,
      </if>
      <if test="PURCHASE_CY_CODE != null and PURCHASE_CY_CODE != emptyBigDecimalValue" >
        PURCHASE_CY_CODE,
      </if>
      <if test="PURCHASE_CY_RATE != null and PURCHASE_CY_RATE != emptyBigDecimalValue" >
        PURCHASE_CY_RATE,
      </if>
      <if test="PURCHASE_CY_UNIT != null and PURCHASE_CY_UNIT != emptyBigDecimalValue" >
        PURCHASE_CY_UNIT,
      </if>
      <if test="PURCHASE_CY_MULT_DIV != null and !&quot;&quot;.equals(PURCHASE_CY_MULT_DIV)" >
        PURCHASE_CY_MULT_DIV,
      </if>
      <if test="SUPP_CODE != null and SUPP_CODE != emptyBigDecimalValue" >
        SUPP_CODE,
      </if>
      <if test="BRANCH_CODE != null and BRANCH_CODE != emptyBigDecimalValue" >
        BRANCH_CODE,
      </if>
      <if test="RETIRE_FR_SL != null and RETIRE_FR_SL != emptyBigDecimalValue" >
        RETIRE_FR_SL,
      </if>
      <if test="VIA_TRX_NBR != null and VIA_TRX_NBR != emptyBigDecimalValue" >
        VIA_TRX_NBR,
      </if>
      <if test="BARCODE != null and !&quot;&quot;.equals(BARCODE)" >
        BARCODE,
      </if>
      <if test="UNIT_PRICE != null and UNIT_PRICE != emptyBigDecimalValue" >
        UNIT_PRICE,
      </if>
      <if test="QTY != null and QTY != emptyBigDecimalValue" >
        QTY,
      </if>
      <if test="ASSET_TYPE != null and ASSET_TYPE != emptyBigDecimalValue" >
        ASSET_TYPE,
      </if>
      <if test="ACQ_CY_CODE != null and ACQ_CY_CODE != emptyBigDecimalValue" >
        ACQ_CY_CODE,
      </if>
      <if test="ACQ_CY_RATE != null and ACQ_CY_RATE != emptyBigDecimalValue" >
        ACQ_CY_RATE,
      </if>
      <if test="ACQ_CY_MULT_DIV != null and !&quot;&quot;.equals(ACQ_CY_MULT_DIV)" >
        ACQ_CY_MULT_DIV,
      </if>
      <if test="ACQ_CV_VALUE != null and ACQ_CV_VALUE != emptyBigDecimalValue" >
        ACQ_CV_VALUE,
      </if>
      <if test="FIELD5 != null and !&quot;&quot;.equals(FIELD5)" >
        FIELD5,
      </if>
      <if test="FIELD6 != null and !&quot;&quot;.equals(FIELD6)" >
        FIELD6,
      </if>
      <if test="OLD_CAPITALIZED_ADD_VALUE != null and OLD_CAPITALIZED_ADD_VALUE != emptyBigDecimalValue" >
        OLD_CAPITALIZED_ADD_VALUE,
      </if>
      <if test="OLD_UTILIZED_PERIOD != null and OLD_UTILIZED_PERIOD != emptyBigDecimalValue" >
        OLD_UTILIZED_PERIOD,
      </if>
      <if test="LEASED_FROM_DATE != null" >
        LEASED_FROM_DATE,
      </if>
      <if test="LEASED_TO_DATE != null" >
        LEASED_TO_DATE,
      </if>
      <if test="MANUFACTURER_SL_NO != null and !&quot;&quot;.equals(MANUFACTURER_SL_NO)" >
        MANUFACTURER_SL_NO,
      </if>
      <if test="LOSS_ON_REVAL != null and LOSS_ON_REVAL != emptyBigDecimalValue" >
        LOSS_ON_REVAL,
      </if>
      <if test="REVAL_RESERVE != null and REVAL_RESERVE != emptyBigDecimalValue" >
        REVAL_RESERVE,
      </if>
      <if test="ANNUAL_DEPREC_RATE != null and ANNUAL_DEPREC_RATE != emptyBigDecimalValue" >
        ANNUAL_DEPREC_RATE,
      </if>
      <if test="DEPRECIATION_BASIS != null and DEPRECIATION_BASIS != emptyBigDecimalValue" >
        DEPRECIATION_BASIS,
      </if>
      <if test="EMP_CODE != null and EMP_CODE != emptyBigDecimalValue" >
        EMP_CODE,
      </if>
      <if test="BARCODE_TYPE != null and !&quot;&quot;.equals(BARCODE_TYPE)" >
        BARCODE_TYPE,
      </if>
      <if test="TAX_AMOUNT != null and TAX_AMOUNT != emptyBigDecimalValue" >
        TAX_AMOUNT,
      </if>
      <if test="FIELD10 != null and !&quot;&quot;.equals(FIELD10)" >
        FIELD10,
      </if>
      <if test="FIELD11 != null and !&quot;&quot;.equals(FIELD11)" >
        FIELD11,
      </if>
      <if test="FIELD12 != null and !&quot;&quot;.equals(FIELD12)" >
        FIELD12,
      </if>
      <if test="FIELD7 != null and !&quot;&quot;.equals(FIELD7)" >
        FIELD7,
      </if>
      <if test="FIELD8 != null and !&quot;&quot;.equals(FIELD8)" >
        FIELD8,
      </if>
      <if test="FIELD9 != null and !&quot;&quot;.equals(FIELD9)" >
        FIELD9,
      </if>
      <if test="LATEST_MARKET_VALUE_FOR_PROV != null and LATEST_MARKET_VALUE_FOR_PROV != emptyBigDecimalValue" >
        LATEST_MARKET_VALUE_FOR_PROV,
      </if>
      <if test="FACILITY_BRANCH != null and FACILITY_BRANCH != emptyBigDecimalValue" >
        FACILITY_BRANCH,
      </if>
      <if test="FACILITY_NO != null and FACILITY_NO != emptyBigDecimalValue" >
        FACILITY_NO,
      </if>
      <if test="SUBLIMIT_NO != null and SUBLIMIT_NO != emptyBigDecimalValue" >
        SUBLIMIT_NO,
      </if>
      <if test="TAX_ANNUAL_DEPRECIATION_RATE != null and TAX_ANNUAL_DEPRECIATION_RATE != emptyBigDecimalValue" >
        TAX_ANNUAL_DEPRECIATION_RATE,
      </if>
      <if test="TAX_DEFAULT_USEFUL_LIFE != null and TAX_DEFAULT_USEFUL_LIFE != emptyBigDecimalValue" >
        TAX_DEFAULT_USEFUL_LIFE,
      </if>
      <if test="TAX_DEPRECIATION_BASIS != null and TAX_DEPRECIATION_BASIS != emptyBigDecimalValue" >
        TAX_DEPRECIATION_BASIS,
      </if>
      <if test="TAX_DEPRECIATION_METHOD != null and TAX_DEPRECIATION_METHOD != emptyBigDecimalValue" >
        TAX_DEPRECIATION_METHOD,
      </if>
      <if test="TAX_INIT_ALLOWANCE_PERC != null and TAX_INIT_ALLOWANCE_PERC != emptyBigDecimalValue" >
        TAX_INIT_ALLOWANCE_PERC,
      </if>
      <if test="LAST_TAX_DEPRECIATION_DATE != null" >
        LAST_TAX_DEPRECIATION_DATE,
      </if>
      <if test="TAX_ACCUMU_DEPRECIATION_VALUE != null and TAX_ACCUMU_DEPRECIATION_VALUE != emptyBigDecimalValue" >
        TAX_ACCUMU_DEPRECIATION_VALUE,
      </if>
      <if test="TAX_DEPRECIATION_RATE != null and TAX_DEPRECIATION_RATE != emptyBigDecimalValue" >
        TAX_DEPRECIATION_RATE,
      </if>
      <if test="TAX_REMAINING_LIFE != null and TAX_REMAINING_LIFE != emptyBigDecimalValue" >
        TAX_REMAINING_LIFE,
      </if>
      <if test="TAX_USEFUL_LIFE != null and TAX_USEFUL_LIFE != emptyBigDecimalValue" >
        TAX_USEFUL_LIFE,
      </if>
      <if test="TAX_UTILIZED_PERIOD != null and TAX_UTILIZED_PERIOD != emptyBigDecimalValue" >
        TAX_UTILIZED_PERIOD,
      </if>
      <if test="ASSET_CY_CODE != null and ASSET_CY_CODE != emptyBigDecimalValue" >
        ASSET_CY_CODE,
      </if>
      <if test="APPROVED_BY != null and !&quot;&quot;.equals(APPROVED_BY)" >
        APPROVED_BY,
      </if>
      <if test="DATE_APPROVED != null" >
        DATE_APPROVED,
      </if>
      <if test="DATE_MODIFIED != null" >
        DATE_MODIFIED,
      </if>
      <if test="MODIFIED_BY != null and !&quot;&quot;.equals(MODIFIED_BY)" >
        MODIFIED_BY,
      </if>
      <if test="SERVER_APPROVED_DATE != null" >
        SERVER_APPROVED_DATE,
      </if>
      <if test="SERVER_MODIFIED_DATE != null" >
        SERVER_MODIFIED_DATE,
      </if>
      <if test="FACILITY_ASSET_LINE_NO != null and FACILITY_ASSET_LINE_NO != emptyBigDecimalValue" >
        FACILITY_ASSET_LINE_NO,
      </if>
      DATE_UPDATED,
      <if test="VENDOR_DOWN_PAYMENT != null and VENDOR_DOWN_PAYMENT != emptyBigDecimalValue" >
        VENDOR_DOWN_PAYMENT,
      </if>
      <if test="SUB_STATUS != null and SUB_STATUS != emptyBigDecimalValue" >
        SUB_STATUS,
      </if>
      <if test="ASSET_SUB_STATUS != null and ASSET_SUB_STATUS != emptyBigDecimalValue" >
        ASSET_SUB_STATUS,
      </if>
      <if test="DOWN_PAYMENT_AMOUNT != null and DOWN_PAYMENT_AMOUNT != emptyBigDecimalValue" >
        DOWN_PAYMENT_AMOUNT,
      </if>
    </trim>
    <trim prefix="values (" suffix=")" suffixOverrides="," >
      <if test="CATEGORY_CODE != null and CATEGORY_CODE != emptyBigDecimalValue" >
        #{CATEGORY_CODE},
      </if>
      <if test="CLASS_CODE != null and CLASS_CODE != emptyBigDecimalValue" >
        #{CLASS_CODE},
      </if>
      <if test="CODE != null and CODE != emptyBigDecimalValue" >
        #{CODE},
      </if>
      <if test="COMP_CODE != null and COMP_CODE != emptyBigDecimalValue" >
        #{COMP_CODE},
      </if>
      <if test="STATUS != null and STATUS != emptyBigDecimalValue" >
        #{STATUS},
      </if>
      <if test="REFERENCE != null and !&quot;&quot;.equals(REFERENCE)" >
        #{REFERENCE},
      </if>
      <if test="LEASE_VALUE != null and LEASE_VALUE != emptyBigDecimalValue" >
        #{LEASE_VALUE},
      </if>
      <if test="USEFUL_LIFE != null and USEFUL_LIFE != emptyBigDecimalValue" >
        #{USEFUL_LIFE},
      </if>
      <if test="UTILIZED_PERIOD != null and UTILIZED_PERIOD != emptyBigDecimalValue" >
        #{UTILIZED_PERIOD},
      </if>
      <if test="REMAINING_LIFE != null and REMAINING_LIFE != emptyBigDecimalValue" >
        #{REMAINING_LIFE},
      </if>
      <if test="LOCATION != null and LOCATION != emptyBigDecimalValue" >
        #{LOCATION},
      </if>
      <if test="ASSIGNED_TO != null and !&quot;&quot;.equals(ASSIGNED_TO)" >
        #{ASSIGNED_TO},
      </if>
      <if test="DATE_ASSIGNED != null" >
        #{DATE_ASSIGNED},
      </if>
      <if test="FIELD1 != null and !&quot;&quot;.equals(FIELD1)" >
        #{FIELD1},
      </if>
      <if test="FIELD2 != null and !&quot;&quot;.equals(FIELD2)" >
        #{FIELD2},
      </if>
      <if test="FIELD3 != null and !&quot;&quot;.equals(FIELD3)" >
        #{FIELD3},
      </if>
      <if test="FIELD4 != null and !&quot;&quot;.equals(FIELD4)" >
        #{FIELD4},
      </if>
      <if test="ACQUISITION_VALUE != null and ACQUISITION_VALUE != emptyBigDecimalValue" >
        #{ACQUISITION_VALUE},
      </if>
      <if test="CAPITALIZED_VALUE != null and CAPITALIZED_VALUE != emptyBigDecimalValue" >
        #{CAPITALIZED_VALUE},
      </if>
      <if test="ACCUMULATED_DEPRECIATION_VALUE != null and ACCUMULATED_DEPRECIATION_VALUE != emptyBigDecimalValue" >
        #{ACCUMULATED_DEPRECIATION_VALUE},
      </if>
      <if test="CAPITALIZED_ADDITIONS_VALUE != null and CAPITALIZED_ADDITIONS_VALUE != emptyBigDecimalValue" >
        #{CAPITALIZED_ADDITIONS_VALUE},
      </if>
      <if test="LATEST_MARKET_VALUE != null and LATEST_MARKET_VALUE != emptyBigDecimalValue" >
        #{LATEST_MARKET_VALUE},
      </if>
      <if test="LATEST_MARKET_DATE != null" >
        #{LATEST_MARKET_DATE},
      </if>
      <if test="DEPRECIATION_RATE != null and DEPRECIATION_RATE != emptyBigDecimalValue" >
        #{DEPRECIATION_RATE},
      </if>
      <if test="DATE_ACQUIRED != null" >
        #{DATE_ACQUIRED},
      </if>
      <if test="ACQUIRED_BY != null and !&quot;&quot;.equals(ACQUIRED_BY)" >
        #{ACQUIRED_BY},
      </if>
      <if test="DATE_CAPITALIZED != null" >
        #{DATE_CAPITALIZED},
      </if>
      <if test="CAPITALIZED_BY != null and !&quot;&quot;.equals(CAPITALIZED_BY)" >
        #{CAPITALIZED_BY},
      </if>
      <if test="DATE_SUSPENDED != null" >
        #{DATE_SUSPENDED},
      </if>
      <if test="SUSPENDED_BY != null and !&quot;&quot;.equals(SUSPENDED_BY)" >
        #{SUSPENDED_BY},
      </if>
      <if test="DATE_RETIRED != null" >
        #{DATE_RETIRED},
      </if>
      <if test="RETIRED_BY != null and !&quot;&quot;.equals(RETIRED_BY)" >
        #{RETIRED_BY},
      </if>
      <if test="DATE_REINSTATED != null" >
        #{DATE_REINSTATED},
      </if>
      <if test="REINSTATED_BY != null and !&quot;&quot;.equals(REINSTATED_BY)" >
        #{REINSTATED_BY},
      </if>
      <if test="DATE_SOLD != null" >
        #{DATE_SOLD},
      </if>
      <if test="SOLD_BY != null and !&quot;&quot;.equals(SOLD_BY)" >
        #{SOLD_BY},
      </if>
      <if test="DATE_REACTIVATED != null" >
        #{DATE_REACTIVATED},
      </if>
      <if test="REACTIVATED_BY != null and !&quot;&quot;.equals(REACTIVATED_BY)" >
        #{REACTIVATED_BY},
      </if>
      <if test="STATUS_TMP != null and STATUS_TMP != emptyBigDecimalValue" >
        #{STATUS_TMP},
      </if>
      <if test="STATUS_TRX != null and STATUS_TRX != emptyBigDecimalValue" >
        #{STATUS_TRX},
      </if>
      <if test="LAST_MAINTENANCE_DATE != null" >
        #{LAST_MAINTENANCE_DATE},
      </if>
      <if test="OWNED_LEASED != null and OWNED_LEASED != emptyBigDecimalValue" >
        #{OWNED_LEASED},
      </if>
      <if test="SALVAGE_VALUE != null and SALVAGE_VALUE != emptyBigDecimalValue" >
        #{SALVAGE_VALUE},
      </if>
      <if test="TRX_DIV_CODE != null and TRX_DIV_CODE != emptyBigDecimalValue" >
        #{TRX_DIV_CODE},
      </if>
      <if test="TRX_DEPT_CODE != null and TRX_DEPT_CODE != emptyBigDecimalValue" >
        #{TRX_DEPT_CODE},
      </if>
      <if test="TRX_TYPE != null and TRX_TYPE != emptyBigDecimalValue" >
        #{TRX_TYPE},
      </if>
      <if test="TRX_NBR != null and TRX_NBR != emptyBigDecimalValue" >
        #{TRX_NBR},
      </if>
      <if test="APPROVED_TRX_DIV_CODE != null and APPROVED_TRX_DIV_CODE != emptyBigDecimalValue" >
        #{APPROVED_TRX_DIV_CODE},
      </if>
      <if test="APPROVED_TRX_DEPT_CODE != null and APPROVED_TRX_DEPT_CODE != emptyBigDecimalValue" >
        #{APPROVED_TRX_DEPT_CODE},
      </if>
      <if test="APPROVED_TRX_TYPE != null and APPROVED_TRX_TYPE != emptyBigDecimalValue" >
        #{APPROVED_TRX_TYPE},
      </if>
      <if test="APPROVED_TRX_NBR != null and APPROVED_TRX_NBR != emptyBigDecimalValue" >
        #{APPROVED_TRX_NBR},
      </if>
      <if test="DEPRECIATION_STATUS != null and DEPRECIATION_STATUS != emptyBigDecimalValue" >
        #{DEPRECIATION_STATUS},
      </if>
      <if test="VALUE_TO_DEPRECIATE != null and !&quot;&quot;.equals(VALUE_TO_DEPRECIATE)" >
        #{VALUE_TO_DEPRECIATE},
      </if>
      <if test="LIFE_TO_DEPRECIATE != null and !&quot;&quot;.equals(LIFE_TO_DEPRECIATE)" >
        #{LIFE_TO_DEPRECIATE},
      </if>
      <if test="OLD_CAPITALIZED_VALUE != null and OLD_CAPITALIZED_VALUE != emptyBigDecimalValue" >
        #{OLD_CAPITALIZED_VALUE},
      </if>
      <if test="OLD_USEFUL_LIFE != null and OLD_USEFUL_LIFE != emptyBigDecimalValue" >
        #{OLD_USEFUL_LIFE},
      </if>
      <if test="LAST_DEPRECIATION_DATE != null" >
        #{LAST_DEPRECIATION_DATE},
      </if>
      <if test="OLD_DEPRECIATION_METHOD != null and OLD_DEPRECIATION_METHOD != emptyBigDecimalValue" >
        #{OLD_DEPRECIATION_METHOD},
      </if>
      <if test="CAPITALIZATION_USEFUL_LIFE != null and CAPITALIZATION_USEFUL_LIFE != emptyBigDecimalValue" >
        #{CAPITALIZATION_USEFUL_LIFE},
      </if>
      <if test="USEFUL_LIFE_FROM != null and USEFUL_LIFE_FROM != emptyBigDecimalValue" >
        #{USEFUL_LIFE_FROM},
      </if>
      <if test="VIA_TRX_TYPE != null and VIA_TRX_TYPE != emptyBigDecimalValue" >
        #{VIA_TRX_TYPE},
      </if>
      <if test="PURCHASE_AMOUNT != null and PURCHASE_AMOUNT != emptyBigDecimalValue" >
        #{PURCHASE_AMOUNT},
      </if>
      <if test="PURCHASE_CY_CODE != null and PURCHASE_CY_CODE != emptyBigDecimalValue" >
        #{PURCHASE_CY_CODE},
      </if>
      <if test="PURCHASE_CY_RATE != null and PURCHASE_CY_RATE != emptyBigDecimalValue" >
        #{PURCHASE_CY_RATE},
      </if>
      <if test="PURCHASE_CY_UNIT != null and PURCHASE_CY_UNIT != emptyBigDecimalValue" >
        #{PURCHASE_CY_UNIT},
      </if>
      <if test="PURCHASE_CY_MULT_DIV != null and !&quot;&quot;.equals(PURCHASE_CY_MULT_DIV)" >
        #{PURCHASE_CY_MULT_DIV},
      </if>
      <if test="SUPP_CODE != null and SUPP_CODE != emptyBigDecimalValue" >
        #{SUPP_CODE},
      </if>
      <if test="BRANCH_CODE != null and BRANCH_CODE != emptyBigDecimalValue" >
        #{BRANCH_CODE},
      </if>
      <if test="RETIRE_FR_SL != null and RETIRE_FR_SL != emptyBigDecimalValue" >
        #{RETIRE_FR_SL},
      </if>
      <if test="VIA_TRX_NBR != null and VIA_TRX_NBR != emptyBigDecimalValue" >
        #{VIA_TRX_NBR},
      </if>
      <if test="BARCODE != null and !&quot;&quot;.equals(BARCODE)" >
        #{BARCODE},
      </if>
      <if test="UNIT_PRICE != null and UNIT_PRICE != emptyBigDecimalValue" >
        #{UNIT_PRICE},
      </if>
      <if test="QTY != null and QTY != emptyBigDecimalValue" >
        #{QTY},
      </if>
      <if test="ASSET_TYPE != null and ASSET_TYPE != emptyBigDecimalValue" >
        #{ASSET_TYPE},
      </if>
      <if test="ACQ_CY_CODE != null and ACQ_CY_CODE != emptyBigDecimalValue" >
        #{ACQ_CY_CODE},
      </if>
      <if test="ACQ_CY_RATE != null and ACQ_CY_RATE != emptyBigDecimalValue" >
        #{ACQ_CY_RATE},
      </if>
      <if test="ACQ_CY_MULT_DIV != null and !&quot;&quot;.equals(ACQ_CY_MULT_DIV)" >
        #{ACQ_CY_MULT_DIV},
      </if>
      <if test="ACQ_CV_VALUE != null and ACQ_CV_VALUE != emptyBigDecimalValue" >
        #{ACQ_CV_VALUE},
      </if>
      <if test="FIELD5 != null and !&quot;&quot;.equals(FIELD5)" >
        #{FIELD5},
      </if>
      <if test="FIELD6 != null and !&quot;&quot;.equals(FIELD6)" >
        #{FIELD6},
      </if>
      <if test="OLD_CAPITALIZED_ADD_VALUE != null and OLD_CAPITALIZED_ADD_VALUE != emptyBigDecimalValue" >
        #{OLD_CAPITALIZED_ADD_VALUE},
      </if>
      <if test="OLD_UTILIZED_PERIOD != null and OLD_UTILIZED_PERIOD != emptyBigDecimalValue" >
        #{OLD_UTILIZED_PERIOD},
      </if>
      <if test="LEASED_FROM_DATE != null" >
        #{LEASED_FROM_DATE},
      </if>
      <if test="LEASED_TO_DATE != null" >
        #{LEASED_TO_DATE},
      </if>
      <if test="MANUFACTURER_SL_NO != null and !&quot;&quot;.equals(MANUFACTURER_SL_NO)" >
        #{MANUFACTURER_SL_NO},
      </if>
      <if test="LOSS_ON_REVAL != null and LOSS_ON_REVAL != emptyBigDecimalValue" >
        #{LOSS_ON_REVAL},
      </if>
      <if test="REVAL_RESERVE != null and REVAL_RESERVE != emptyBigDecimalValue" >
        #{REVAL_RESERVE},
      </if>
      <if test="ANNUAL_DEPREC_RATE != null and ANNUAL_DEPREC_RATE != emptyBigDecimalValue" >
        #{ANNUAL_DEPREC_RATE},
      </if>
      <if test="DEPRECIATION_BASIS != null and DEPRECIATION_BASIS != emptyBigDecimalValue" >
        #{DEPRECIATION_BASIS},
      </if>
      <if test="EMP_CODE != null and EMP_CODE != emptyBigDecimalValue" >
        #{EMP_CODE},
      </if>
      <if test="BARCODE_TYPE != null and !&quot;&quot;.equals(BARCODE_TYPE)" >
        #{BARCODE_TYPE},
      </if>
      <if test="TAX_AMOUNT != null and TAX_AMOUNT != emptyBigDecimalValue" >
        #{TAX_AMOUNT},
      </if>
      <if test="FIELD10 != null and !&quot;&quot;.equals(FIELD10)" >
        #{FIELD10},
      </if>
      <if test="FIELD11 != null and !&quot;&quot;.equals(FIELD11)" >
        #{FIELD11},
      </if>
      <if test="FIELD12 != null and !&quot;&quot;.equals(FIELD12)" >
        #{FIELD12},
      </if>
      <if test="FIELD7 != null and !&quot;&quot;.equals(FIELD7)" >
        #{FIELD7},
      </if>
      <if test="FIELD8 != null and !&quot;&quot;.equals(FIELD8)" >
        #{FIELD8},
      </if>
      <if test="FIELD9 != null and !&quot;&quot;.equals(FIELD9)" >
        #{FIELD9},
      </if>
      <if test="LATEST_MARKET_VALUE_FOR_PROV != null and LATEST_MARKET_VALUE_FOR_PROV != emptyBigDecimalValue" >
        #{LATEST_MARKET_VALUE_FOR_PROV},
      </if>
      <if test="FACILITY_BRANCH != null and FACILITY_BRANCH != emptyBigDecimalValue" >
        #{FACILITY_BRANCH},
      </if>
      <if test="FACILITY_NO != null and FACILITY_NO != emptyBigDecimalValue" >
        #{FACILITY_NO},
      </if>
      <if test="SUBLIMIT_NO != null and SUBLIMIT_NO != emptyBigDecimalValue" >
        #{SUBLIMIT_NO},
      </if>
      <if test="TAX_ANNUAL_DEPRECIATION_RATE != null and TAX_ANNUAL_DEPRECIATION_RATE != emptyBigDecimalValue" >
        #{TAX_ANNUAL_DEPRECIATION_RATE},
      </if>
      <if test="TAX_DEFAULT_USEFUL_LIFE != null and TAX_DEFAULT_USEFUL_LIFE != emptyBigDecimalValue" >
        #{TAX_DEFAULT_USEFUL_LIFE},
      </if>
      <if test="TAX_DEPRECIATION_BASIS != null and TAX_DEPRECIATION_BASIS != emptyBigDecimalValue" >
        #{TAX_DEPRECIATION_BASIS},
      </if>
      <if test="TAX_DEPRECIATION_METHOD != null and TAX_DEPRECIATION_METHOD != emptyBigDecimalValue" >
        #{TAX_DEPRECIATION_METHOD},
      </if>
      <if test="TAX_INIT_ALLOWANCE_PERC != null and TAX_INIT_ALLOWANCE_PERC != emptyBigDecimalValue" >
        #{TAX_INIT_ALLOWANCE_PERC},
      </if>
      <if test="LAST_TAX_DEPRECIATION_DATE != null" >
        #{LAST_TAX_DEPRECIATION_DATE},
      </if>
      <if test="TAX_ACCUMU_DEPRECIATION_VALUE != null and TAX_ACCUMU_DEPRECIATION_VALUE != emptyBigDecimalValue" >
        #{TAX_ACCUMU_DEPRECIATION_VALUE},
      </if>
      <if test="TAX_DEPRECIATION_RATE != null and TAX_DEPRECIATION_RATE != emptyBigDecimalValue" >
        #{TAX_DEPRECIATION_RATE},
      </if>
      <if test="TAX_REMAINING_LIFE != null and TAX_REMAINING_LIFE != emptyBigDecimalValue" >
        #{TAX_REMAINING_LIFE},
      </if>
      <if test="TAX_USEFUL_LIFE != null and TAX_USEFUL_LIFE != emptyBigDecimalValue" >
        #{TAX_USEFUL_LIFE},
      </if>
      <if test="TAX_UTILIZED_PERIOD != null and TAX_UTILIZED_PERIOD != emptyBigDecimalValue" >
        #{TAX_UTILIZED_PERIOD},
      </if>
      <if test="ASSET_CY_CODE != null and ASSET_CY_CODE != emptyBigDecimalValue" >
        #{ASSET_CY_CODE},
      </if>
      <if test="APPROVED_BY != null and !&quot;&quot;.equals(APPROVED_BY)" >
        #{APPROVED_BY},
      </if>
      <if test="DATE_APPROVED != null" >
        #{DATE_APPROVED},
      </if>
      <if test="DATE_MODIFIED != null" >
        #{DATE_MODIFIED},
      </if>
      <if test="MODIFIED_BY != null and !&quot;&quot;.equals(MODIFIED_BY)" >
        #{MODIFIED_BY},
      </if>
      <if test="SERVER_APPROVED_DATE != null" >
        #{SERVER_APPROVED_DATE},
      </if>
      <if test="SERVER_MODIFIED_DATE != null" >
        #{SERVER_MODIFIED_DATE},
      </if>
      <if test="FACILITY_ASSET_LINE_NO != null and FACILITY_ASSET_LINE_NO != emptyBigDecimalValue" >
        #{FACILITY_ASSET_LINE_NO},
      </if>
      <choose >
        <when test="isSybase == 1" >
           GETDATE(),
        </when>
        <otherwise >
           SYSDATE,
        </otherwise>
      </choose>
      <if test="VENDOR_DOWN_PAYMENT != null and VENDOR_DOWN_PAYMENT != emptyBigDecimalValue" >
        #{VENDOR_DOWN_PAYMENT},
      </if>
      <if test="SUB_STATUS != null and SUB_STATUS != emptyBigDecimalValue" >
        #{SUB_STATUS},
      </if>
      <if test="ASSET_SUB_STATUS != null and ASSET_SUB_STATUS != emptyBigDecimalValue" >
        #{ASSET_SUB_STATUS},
      </if>
      <if test="DOWN_PAYMENT_AMOUNT != null and DOWN_PAYMENT_AMOUNT != emptyBigDecimalValue" >
        #{DOWN_PAYMENT_AMOUNT},
      </if>
    </trim>
  </insert>
  <sql id="sql_updateFASAST" >
    update FASAST
    <set >
      <if test="STATUS != null" >
        <choose >
          <when test="STATUS == emptyBigDecimalValue" >
            STATUS = NULL ,
          </when>
          <otherwise >
            STATUS = #{STATUS},
          </otherwise>
        </choose>
      </if>
      <if test="REFERENCE != null" >
        <choose >
          <when test="REFERENCE.equals(&quot;&quot;)" >
            REFERENCE = NULL ,
          </when>
          <otherwise >
            REFERENCE = #{REFERENCE},
          </otherwise>
        </choose>
      </if>
      <if test="LEASE_VALUE != null" >
        <choose >
          <when test="LEASE_VALUE == emptyBigDecimalValue" >
            LEASE_VALUE = NULL ,
          </when>
          <otherwise >
            LEASE_VALUE = #{LEASE_VALUE},
          </otherwise>
        </choose>
      </if>
      <if test="USEFUL_LIFE != null" >
        <choose >
          <when test="USEFUL_LIFE == emptyBigDecimalValue" >
            USEFUL_LIFE = NULL ,
          </when>
          <otherwise >
            USEFUL_LIFE = #{USEFUL_LIFE},
          </otherwise>
        </choose>
      </if>
      <if test="UTILIZED_PERIOD != null" >
        <choose >
          <when test="UTILIZED_PERIOD == emptyBigDecimalValue" >
            UTILIZED_PERIOD = NULL ,
          </when>
          <otherwise >
            UTILIZED_PERIOD = #{UTILIZED_PERIOD},
          </otherwise>
        </choose>
      </if>
      <if test="REMAINING_LIFE != null" >
        <choose >
          <when test="REMAINING_LIFE == emptyBigDecimalValue" >
            REMAINING_LIFE = NULL ,
          </when>
          <otherwise >
            REMAINING_LIFE = #{REMAINING_LIFE},
          </otherwise>
        </choose>
      </if>
      <if test="LOCATION != null" >
        <choose >
          <when test="LOCATION == emptyBigDecimalValue" >
            LOCATION = NULL ,
          </when>
          <otherwise >
            LOCATION = #{LOCATION},
          </otherwise>
        </choose>
      </if>
      <if test="ASSIGNED_TO != null" >
        <choose >
          <when test="ASSIGNED_TO.equals(&quot;&quot;)" >
            ASSIGNED_TO = NULL ,
          </when>
          <otherwise >
            ASSIGNED_TO = #{ASSIGNED_TO},
          </otherwise>
        </choose>
      </if>
      <if test="DATE_ASSIGNED != null" >
        DATE_ASSIGNED = #{DATE_ASSIGNED},
      </if>
      <if test="FIELD1 != null" >
        <choose >
          <when test="FIELD1.equals(&quot;&quot;)" >
            FIELD1 = NULL ,
          </when>
          <otherwise >
            FIELD1 = #{FIELD1},
          </otherwise>
        </choose>
      </if>
      <if test="FIELD2 != null" >
        <choose >
          <when test="FIELD2.equals(&quot;&quot;)" >
            FIELD2 = NULL ,
          </when>
          <otherwise >
            FIELD2 = #{FIELD2},
          </otherwise>
        </choose>
      </if>
      <if test="FIELD3 != null" >
        <choose >
          <when test="FIELD3.equals(&quot;&quot;)" >
            FIELD3 = NULL ,
          </when>
          <otherwise >
            FIELD3 = #{FIELD3},
          </otherwise>
        </choose>
      </if>
      <if test="FIELD4 != null" >
        <choose >
          <when test="FIELD4.equals(&quot;&quot;)" >
            FIELD4 = NULL ,
          </when>
          <otherwise >
            FIELD4 = #{FIELD4},
          </otherwise>
        </choose>
      </if>
      <if test="ACQUISITION_VALUE != null" >
        <choose >
          <when test="ACQUISITION_VALUE == emptyBigDecimalValue" >
            ACQUISITION_VALUE = NULL ,
          </when>
          <otherwise >
            ACQUISITION_VALUE = #{ACQUISITION_VALUE},
          </otherwise>
        </choose>
      </if>
      <if test="CAPITALIZED_VALUE != null" >
        <choose >
          <when test="CAPITALIZED_VALUE == emptyBigDecimalValue" >
            CAPITALIZED_VALUE = NULL ,
          </when>
          <otherwise >
            CAPITALIZED_VALUE = #{CAPITALIZED_VALUE},
          </otherwise>
        </choose>
      </if>
      <if test="ACCUMULATED_DEPRECIATION_VALUE != null" >
        <choose >
          <when test="ACCUMULATED_DEPRECIATION_VALUE == emptyBigDecimalValue" >
            ACCUMULATED_DEPRECIATION_VALUE = NULL ,
          </when>
          <otherwise >
            ACCUMULATED_DEPRECIATION_VALUE = #{ACCUMULATED_DEPRECIATION_VALUE},
          </otherwise>
        </choose>
      </if>
      <if test="CAPITALIZED_ADDITIONS_VALUE != null" >
        <choose >
          <when test="CAPITALIZED_ADDITIONS_VALUE == emptyBigDecimalValue" >
            CAPITALIZED_ADDITIONS_VALUE = NULL ,
          </when>
          <otherwise >
            CAPITALIZED_ADDITIONS_VALUE = #{CAPITALIZED_ADDITIONS_VALUE},
          </otherwise>
        </choose>
      </if>
      <if test="LATEST_MARKET_VALUE != null" >
        <choose >
          <when test="LATEST_MARKET_VALUE == emptyBigDecimalValue" >
            LATEST_MARKET_VALUE = NULL ,
          </when>
          <otherwise >
            LATEST_MARKET_VALUE = #{LATEST_MARKET_VALUE},
          </otherwise>
        </choose>
      </if>
      <if test="LATEST_MARKET_DATE != null" >
        LATEST_MARKET_DATE = #{LATEST_MARKET_DATE},
      </if>
      <if test="DEPRECIATION_RATE != null" >
        <choose >
          <when test="DEPRECIATION_RATE == emptyBigDecimalValue" >
            DEPRECIATION_RATE = NULL ,
          </when>
          <otherwise >
            DEPRECIATION_RATE = #{DEPRECIATION_RATE},
          </otherwise>
        </choose>
      </if>
      <if test="DATE_ACQUIRED != null" >
        DATE_ACQUIRED = #{DATE_ACQUIRED},
      </if>
      <if test="ACQUIRED_BY != null" >
        <choose >
          <when test="ACQUIRED_BY.equals(&quot;&quot;)" >
            ACQUIRED_BY = NULL ,
          </when>
          <otherwise >
            ACQUIRED_BY = #{ACQUIRED_BY},
          </otherwise>
        </choose>
      </if>
      <if test="DATE_CAPITALIZED != null" >
        DATE_CAPITALIZED = #{DATE_CAPITALIZED},
      </if>
      <if test="CAPITALIZED_BY != null" >
        <choose >
          <when test="CAPITALIZED_BY.equals(&quot;&quot;)" >
            CAPITALIZED_BY = NULL ,
          </when>
          <otherwise >
            CAPITALIZED_BY = #{CAPITALIZED_BY},
          </otherwise>
        </choose>
      </if>
      <if test="DATE_SUSPENDED != null" >
        DATE_SUSPENDED = #{DATE_SUSPENDED},
      </if>
      <if test="SUSPENDED_BY != null" >
        <choose >
          <when test="SUSPENDED_BY.equals(&quot;&quot;)" >
            SUSPENDED_BY = NULL ,
          </when>
          <otherwise >
            SUSPENDED_BY = #{SUSPENDED_BY},
          </otherwise>
        </choose>
      </if>
      <if test="DATE_RETIRED != null" >
        DATE_RETIRED = #{DATE_RETIRED},
      </if>
      <if test="RETIRED_BY != null" >
        <choose >
          <when test="RETIRED_BY.equals(&quot;&quot;)" >
            RETIRED_BY = NULL ,
          </when>
          <otherwise >
            RETIRED_BY = #{RETIRED_BY},
          </otherwise>
        </choose>
      </if>
      <if test="DATE_REINSTATED != null" >
        DATE_REINSTATED = #{DATE_REINSTATED},
      </if>
      <if test="REINSTATED_BY != null" >
        <choose >
          <when test="REINSTATED_BY.equals(&quot;&quot;)" >
            REINSTATED_BY = NULL ,
          </when>
          <otherwise >
            REINSTATED_BY = #{REINSTATED_BY},
          </otherwise>
        </choose>
      </if>
      <if test="DATE_SOLD != null" >
        DATE_SOLD = #{DATE_SOLD},
      </if>
      <if test="SOLD_BY != null" >
        <choose >
          <when test="SOLD_BY.equals(&quot;&quot;)" >
            SOLD_BY = NULL ,
          </when>
          <otherwise >
            SOLD_BY = #{SOLD_BY},
          </otherwise>
        </choose>
      </if>
      <if test="DATE_REACTIVATED != null" >
        DATE_REACTIVATED = #{DATE_REACTIVATED},
      </if>
      <if test="REACTIVATED_BY != null" >
        <choose >
          <when test="REACTIVATED_BY.equals(&quot;&quot;)" >
            REACTIVATED_BY = NULL ,
          </when>
          <otherwise >
            REACTIVATED_BY = #{REACTIVATED_BY},
          </otherwise>
        </choose>
      </if>
      <if test="STATUS_TMP != null" >
        <choose >
          <when test="STATUS_TMP == emptyBigDecimalValue" >
            STATUS_TMP = NULL ,
          </when>
          <otherwise >
            STATUS_TMP = #{STATUS_TMP},
          </otherwise>
        </choose>
      </if>
      <if test="STATUS_TRX != null" >
        <choose >
          <when test="STATUS_TRX == emptyBigDecimalValue" >
            STATUS_TRX = NULL ,
          </when>
          <otherwise >
            STATUS_TRX = #{STATUS_TRX},
          </otherwise>
        </choose>
      </if>
      <if test="LAST_MAINTENANCE_DATE != null" >
        LAST_MAINTENANCE_DATE = #{LAST_MAINTENANCE_DATE},
      </if>
      <if test="OWNED_LEASED != null" >
        <choose >
          <when test="OWNED_LEASED == emptyBigDecimalValue" >
            OWNED_LEASED = NULL ,
          </when>
          <otherwise >
            OWNED_LEASED = #{OWNED_LEASED},
          </otherwise>
        </choose>
      </if>
      <if test="SALVAGE_VALUE != null" >
        <choose >
          <when test="SALVAGE_VALUE == emptyBigDecimalValue" >
            SALVAGE_VALUE = NULL ,
          </when>
          <otherwise >
            SALVAGE_VALUE = #{SALVAGE_VALUE},
          </otherwise>
        </choose>
      </if>
      <if test="TRX_DIV_CODE != null" >
        <choose >
          <when test="TRX_DIV_CODE == emptyBigDecimalValue" >
            TRX_DIV_CODE = NULL ,
          </when>
          <otherwise >
            TRX_DIV_CODE = #{TRX_DIV_CODE},
          </otherwise>
        </choose>
      </if>
      <if test="TRX_DEPT_CODE != null" >
        <choose >
          <when test="TRX_DEPT_CODE == emptyBigDecimalValue" >
            TRX_DEPT_CODE = NULL ,
          </when>
          <otherwise >
            TRX_DEPT_CODE = #{TRX_DEPT_CODE},
          </otherwise>
        </choose>
      </if>
      <if test="TRX_TYPE != null" >
        <choose >
          <when test="TRX_TYPE == emptyBigDecimalValue" >
            TRX_TYPE = NULL ,
          </when>
          <otherwise >
            TRX_TYPE = #{TRX_TYPE},
          </otherwise>
        </choose>
      </if>
      <if test="TRX_NBR != null" >
        <choose >
          <when test="TRX_NBR == emptyBigDecimalValue" >
            TRX_NBR = NULL ,
          </when>
          <otherwise >
            TRX_NBR = #{TRX_NBR},
          </otherwise>
        </choose>
      </if>
      <if test="APPROVED_TRX_DIV_CODE != null" >
        <choose >
          <when test="APPROVED_TRX_DIV_CODE == emptyBigDecimalValue" >
            APPROVED_TRX_DIV_CODE = NULL ,
          </when>
          <otherwise >
            APPROVED_TRX_DIV_CODE = #{APPROVED_TRX_DIV_CODE},
          </otherwise>
        </choose>
      </if>
      <if test="APPROVED_TRX_DEPT_CODE != null" >
        <choose >
          <when test="APPROVED_TRX_DEPT_CODE == emptyBigDecimalValue" >
            APPROVED_TRX_DEPT_CODE = NULL ,
          </when>
          <otherwise >
            APPROVED_TRX_DEPT_CODE = #{APPROVED_TRX_DEPT_CODE},
          </otherwise>
        </choose>
      </if>
      <if test="APPROVED_TRX_TYPE != null" >
        <choose >
          <when test="APPROVED_TRX_TYPE == emptyBigDecimalValue" >
            APPROVED_TRX_TYPE = NULL ,
          </when>
          <otherwise >
            APPROVED_TRX_TYPE = #{APPROVED_TRX_TYPE},
          </otherwise>
        </choose>
      </if>
      <if test="APPROVED_TRX_NBR != null" >
        <choose >
          <when test="APPROVED_TRX_NBR == emptyBigDecimalValue" >
            APPROVED_TRX_NBR = NULL ,
          </when>
          <otherwise >
            APPROVED_TRX_NBR = #{APPROVED_TRX_NBR},
          </otherwise>
        </choose>
      </if>
      <if test="DEPRECIATION_STATUS != null" >
        <choose >
          <when test="DEPRECIATION_STATUS == emptyBigDecimalValue" >
            DEPRECIATION_STATUS = NULL ,
          </when>
          <otherwise >
            DEPRECIATION_STATUS = #{DEPRECIATION_STATUS},
          </otherwise>
        </choose>
      </if>
      <if test="VALUE_TO_DEPRECIATE != null" >
        <choose >
          <when test="VALUE_TO_DEPRECIATE.equals(&quot;&quot;)" >
            VALUE_TO_DEPRECIATE = NULL ,
          </when>
          <otherwise >
            VALUE_TO_DEPRECIATE = #{VALUE_TO_DEPRECIATE},
          </otherwise>
        </choose>
      </if>
      <if test="LIFE_TO_DEPRECIATE != null" >
        <choose >
          <when test="LIFE_TO_DEPRECIATE.equals(&quot;&quot;)" >
            LIFE_TO_DEPRECIATE = NULL ,
          </when>
          <otherwise >
            LIFE_TO_DEPRECIATE = #{LIFE_TO_DEPRECIATE},
          </otherwise>
        </choose>
      </if>
      <if test="OLD_CAPITALIZED_VALUE != null" >
        <choose >
          <when test="OLD_CAPITALIZED_VALUE == emptyBigDecimalValue" >
            OLD_CAPITALIZED_VALUE = NULL ,
          </when>
          <otherwise >
            OLD_CAPITALIZED_VALUE = #{OLD_CAPITALIZED_VALUE},
          </otherwise>
        </choose>
      </if>
      <if test="OLD_USEFUL_LIFE != null" >
        <choose >
          <when test="OLD_USEFUL_LIFE == emptyBigDecimalValue" >
            OLD_USEFUL_LIFE = NULL ,
          </when>
          <otherwise >
            OLD_USEFUL_LIFE = #{OLD_USEFUL_LIFE},
          </otherwise>
        </choose>
      </if>
      <if test="LAST_DEPRECIATION_DATE != null" >
        LAST_DEPRECIATION_DATE = #{LAST_DEPRECIATION_DATE},
      </if>
      <if test="OLD_DEPRECIATION_METHOD != null" >
        <choose >
          <when test="OLD_DEPRECIATION_METHOD == emptyBigDecimalValue" >
            OLD_DEPRECIATION_METHOD = NULL ,
          </when>
          <otherwise >
            OLD_DEPRECIATION_METHOD = #{OLD_DEPRECIATION_METHOD},
          </otherwise>
        </choose>
      </if>
      <if test="CAPITALIZATION_USEFUL_LIFE != null" >
        <choose >
          <when test="CAPITALIZATION_USEFUL_LIFE == emptyBigDecimalValue" >
            CAPITALIZATION_USEFUL_LIFE = NULL ,
          </when>
          <otherwise >
            CAPITALIZATION_USEFUL_LIFE = #{CAPITALIZATION_USEFUL_LIFE},
          </otherwise>
        </choose>
      </if>
      <if test="USEFUL_LIFE_FROM != null" >
        <choose >
          <when test="USEFUL_LIFE_FROM == emptyBigDecimalValue" >
            USEFUL_LIFE_FROM = NULL ,
          </when>
          <otherwise >
            USEFUL_LIFE_FROM = #{USEFUL_LIFE_FROM},
          </otherwise>
        </choose>
      </if>
      <if test="VIA_TRX_TYPE != null" >
        <choose >
          <when test="VIA_TRX_TYPE == emptyBigDecimalValue" >
            VIA_TRX_TYPE = NULL ,
          </when>
          <otherwise >
            VIA_TRX_TYPE = #{VIA_TRX_TYPE},
          </otherwise>
        </choose>
      </if>
      <if test="PURCHASE_AMOUNT != null" >
        <choose >
          <when test="PURCHASE_AMOUNT == emptyBigDecimalValue" >
            PURCHASE_AMOUNT = NULL ,
          </when>
          <otherwise >
            PURCHASE_AMOUNT = #{PURCHASE_AMOUNT},
          </otherwise>
        </choose>
      </if>
      <if test="PURCHASE_CY_CODE != null" >
        <choose >
          <when test="PURCHASE_CY_CODE == emptyBigDecimalValue" >
            PURCHASE_CY_CODE = NULL ,
          </when>
          <otherwise >
            PURCHASE_CY_CODE = #{PURCHASE_CY_CODE},
          </otherwise>
        </choose>
      </if>
      <if test="PURCHASE_CY_RATE != null" >
        <choose >
          <when test="PURCHASE_CY_RATE == emptyBigDecimalValue" >
            PURCHASE_CY_RATE = NULL ,
          </when>
          <otherwise >
            PURCHASE_CY_RATE = #{PURCHASE_CY_RATE},
          </otherwise>
        </choose>
      </if>
      <if test="PURCHASE_CY_UNIT != null" >
        <choose >
          <when test="PURCHASE_CY_UNIT == emptyBigDecimalValue" >
            PURCHASE_CY_UNIT = NULL ,
          </when>
          <otherwise >
            PURCHASE_CY_UNIT = #{PURCHASE_CY_UNIT},
          </otherwise>
        </choose>
      </if>
      <if test="PURCHASE_CY_MULT_DIV != null" >
        <choose >
          <when test="PURCHASE_CY_MULT_DIV.equals(&quot;&quot;)" >
            PURCHASE_CY_MULT_DIV = NULL ,
          </when>
          <otherwise >
            PURCHASE_CY_MULT_DIV = #{PURCHASE_CY_MULT_DIV},
          </otherwise>
        </choose>
      </if>
      <if test="SUPP_CODE != null" >
        <choose >
          <when test="SUPP_CODE == emptyBigDecimalValue" >
            SUPP_CODE = NULL ,
          </when>
          <otherwise >
            SUPP_CODE = #{SUPP_CODE},
          </otherwise>
        </choose>
      </if>
      <if test="BRANCH_CODE != null" >
        <choose >
          <when test="BRANCH_CODE == emptyBigDecimalValue" >
            BRANCH_CODE = NULL ,
          </when>
          <otherwise >
            BRANCH_CODE = #{BRANCH_CODE},
          </otherwise>
        </choose>
      </if>
      <if test="RETIRE_FR_SL != null" >
        <choose >
          <when test="RETIRE_FR_SL == emptyBigDecimalValue" >
            RETIRE_FR_SL = NULL ,
          </when>
          <otherwise >
            RETIRE_FR_SL = #{RETIRE_FR_SL},
          </otherwise>
        </choose>
      </if>
      <if test="VIA_TRX_NBR != null" >
        <choose >
          <when test="VIA_TRX_NBR == emptyBigDecimalValue" >
            VIA_TRX_NBR = NULL ,
          </when>
          <otherwise >
            VIA_TRX_NBR = #{VIA_TRX_NBR},
          </otherwise>
        </choose>
      </if>
      <if test="BARCODE != null" >
        <choose >
          <when test="BARCODE.equals(&quot;&quot;)" >
            BARCODE = NULL ,
          </when>
          <otherwise >
            BARCODE = #{BARCODE},
          </otherwise>
        </choose>
      </if>
      <if test="UNIT_PRICE != null" >
        <choose >
          <when test="UNIT_PRICE == emptyBigDecimalValue" >
            UNIT_PRICE = NULL ,
          </when>
          <otherwise >
            UNIT_PRICE = #{UNIT_PRICE},
          </otherwise>
        </choose>
      </if>
      <if test="QTY != null" >
        <choose >
          <when test="QTY == emptyBigDecimalValue" >
            QTY = NULL ,
          </when>
          <otherwise >
            QTY = #{QTY},
          </otherwise>
        </choose>
      </if>
      <if test="ASSET_TYPE != null" >
        <choose >
          <when test="ASSET_TYPE == emptyBigDecimalValue" >
            ASSET_TYPE = NULL ,
          </when>
          <otherwise >
            ASSET_TYPE = #{ASSET_TYPE},
          </otherwise>
        </choose>
      </if>
      <if test="ACQ_CY_CODE != null" >
        <choose >
          <when test="ACQ_CY_CODE == emptyBigDecimalValue" >
            ACQ_CY_CODE = NULL ,
          </when>
          <otherwise >
            ACQ_CY_CODE = #{ACQ_CY_CODE},
          </otherwise>
        </choose>
      </if>
      <if test="ACQ_CY_RATE != null" >
        <choose >
          <when test="ACQ_CY_RATE == emptyBigDecimalValue" >
            ACQ_CY_RATE = NULL ,
          </when>
          <otherwise >
            ACQ_CY_RATE = #{ACQ_CY_RATE},
          </otherwise>
        </choose>
      </if>
      <if test="ACQ_CY_MULT_DIV != null" >
        <choose >
          <when test="ACQ_CY_MULT_DIV.equals(&quot;&quot;)" >
            ACQ_CY_MULT_DIV = NULL ,
          </when>
          <otherwise >
            ACQ_CY_MULT_DIV = #{ACQ_CY_MULT_DIV},
          </otherwise>
        </choose>
      </if>
      <if test="ACQ_CV_VALUE != null" >
        <choose >
          <when test="ACQ_CV_VALUE == emptyBigDecimalValue" >
            ACQ_CV_VALUE = NULL ,
          </when>
          <otherwise >
            ACQ_CV_VALUE = #{ACQ_CV_VALUE},
          </otherwise>
        </choose>
      </if>
      <if test="FIELD5 != null" >
        <choose >
          <when test="FIELD5.equals(&quot;&quot;)" >
            FIELD5 = NULL ,
          </when>
          <otherwise >
            FIELD5 = #{FIELD5},
          </otherwise>
        </choose>
      </if>
      <if test="FIELD6 != null" >
        <choose >
          <when test="FIELD6.equals(&quot;&quot;)" >
            FIELD6 = NULL ,
          </when>
          <otherwise >
            FIELD6 = #{FIELD6},
          </otherwise>
        </choose>
      </if>
      <if test="OLD_CAPITALIZED_ADD_VALUE != null" >
        <choose >
          <when test="OLD_CAPITALIZED_ADD_VALUE == emptyBigDecimalValue" >
            OLD_CAPITALIZED_ADD_VALUE = NULL ,
          </when>
          <otherwise >
            OLD_CAPITALIZED_ADD_VALUE = #{OLD_CAPITALIZED_ADD_VALUE},
          </otherwise>
        </choose>
      </if>
      <if test="OLD_UTILIZED_PERIOD != null" >
        <choose >
          <when test="OLD_UTILIZED_PERIOD == emptyBigDecimalValue" >
            OLD_UTILIZED_PERIOD = NULL ,
          </when>
          <otherwise >
            OLD_UTILIZED_PERIOD = #{OLD_UTILIZED_PERIOD},
          </otherwise>
        </choose>
      </if>
      <if test="LEASED_FROM_DATE != null" >
        LEASED_FROM_DATE = #{LEASED_FROM_DATE},
      </if>
      <if test="LEASED_TO_DATE != null" >
        LEASED_TO_DATE = #{LEASED_TO_DATE},
      </if>
      <if test="MANUFACTURER_SL_NO != null" >
        <choose >
          <when test="MANUFACTURER_SL_NO.equals(&quot;&quot;)" >
            MANUFACTURER_SL_NO = NULL ,
          </when>
          <otherwise >
            MANUFACTURER_SL_NO = #{MANUFACTURER_SL_NO},
          </otherwise>
        </choose>
      </if>
      <if test="LOSS_ON_REVAL != null" >
        <choose >
          <when test="LOSS_ON_REVAL == emptyBigDecimalValue" >
            LOSS_ON_REVAL = NULL ,
          </when>
          <otherwise >
            LOSS_ON_REVAL = #{LOSS_ON_REVAL},
          </otherwise>
        </choose>
      </if>
      <if test="REVAL_RESERVE != null" >
        <choose >
          <when test="REVAL_RESERVE == emptyBigDecimalValue" >
            REVAL_RESERVE = NULL ,
          </when>
          <otherwise >
            REVAL_RESERVE = #{REVAL_RESERVE},
          </otherwise>
        </choose>
      </if>
      <if test="ANNUAL_DEPREC_RATE != null" >
        <choose >
          <when test="ANNUAL_DEPREC_RATE == emptyBigDecimalValue" >
            ANNUAL_DEPREC_RATE = NULL ,
          </when>
          <otherwise >
            ANNUAL_DEPREC_RATE = #{ANNUAL_DEPREC_RATE},
          </otherwise>
        </choose>
      </if>
      <if test="DEPRECIATION_BASIS != null" >
        <choose >
          <when test="DEPRECIATION_BASIS == emptyBigDecimalValue" >
            DEPRECIATION_BASIS = NULL ,
          </when>
          <otherwise >
            DEPRECIATION_BASIS = #{DEPRECIATION_BASIS},
          </otherwise>
        </choose>
      </if>
      <if test="EMP_CODE != null" >
        <choose >
          <when test="EMP_CODE == emptyBigDecimalValue" >
            EMP_CODE = NULL ,
          </when>
          <otherwise >
            EMP_CODE = #{EMP_CODE},
          </otherwise>
        </choose>
      </if>
      <if test="BARCODE_TYPE != null" >
        <choose >
          <when test="BARCODE_TYPE.equals(&quot;&quot;)" >
            BARCODE_TYPE = NULL ,
          </when>
          <otherwise >
            BARCODE_TYPE = #{BARCODE_TYPE},
          </otherwise>
        </choose>
      </if>
      <if test="TAX_AMOUNT != null" >
        <choose >
          <when test="TAX_AMOUNT == emptyBigDecimalValue" >
            TAX_AMOUNT = NULL ,
          </when>
          <otherwise >
            TAX_AMOUNT = #{TAX_AMOUNT},
          </otherwise>
        </choose>
      </if>
      <if test="FIELD10 != null" >
        <choose >
          <when test="FIELD10.equals(&quot;&quot;)" >
            FIELD10 = NULL ,
          </when>
          <otherwise >
            FIELD10 = #{FIELD10},
          </otherwise>
        </choose>
      </if>
      <if test="FIELD11 != null" >
        <choose >
          <when test="FIELD11.equals(&quot;&quot;)" >
            FIELD11 = NULL ,
          </when>
          <otherwise >
            FIELD11 = #{FIELD11},
          </otherwise>
        </choose>
      </if>
      <if test="FIELD12 != null" >
        <choose >
          <when test="FIELD12.equals(&quot;&quot;)" >
            FIELD12 = NULL ,
          </when>
          <otherwise >
            FIELD12 = #{FIELD12},
          </otherwise>
        </choose>
      </if>
      <if test="FIELD7 != null" >
        <choose >
          <when test="FIELD7.equals(&quot;&quot;)" >
            FIELD7 = NULL ,
          </when>
          <otherwise >
            FIELD7 = #{FIELD7},
          </otherwise>
        </choose>
      </if>
      <if test="FIELD8 != null" >
        <choose >
          <when test="FIELD8.equals(&quot;&quot;)" >
            FIELD8 = NULL ,
          </when>
          <otherwise >
            FIELD8 = #{FIELD8},
          </otherwise>
        </choose>
      </if>
      <if test="FIELD9 != null" >
        <choose >
          <when test="FIELD9.equals(&quot;&quot;)" >
            FIELD9 = NULL ,
          </when>
          <otherwise >
            FIELD9 = #{FIELD9},
          </otherwise>
        </choose>
      </if>
      <if test="LATEST_MARKET_VALUE_FOR_PROV != null" >
        <choose >
          <when test="LATEST_MARKET_VALUE_FOR_PROV == emptyBigDecimalValue" >
            LATEST_MARKET_VALUE_FOR_PROV = NULL ,
          </when>
          <otherwise >
            LATEST_MARKET_VALUE_FOR_PROV = #{LATEST_MARKET_VALUE_FOR_PROV},
          </otherwise>
        </choose>
      </if>
      <if test="FACILITY_BRANCH != null" >
        <choose >
          <when test="FACILITY_BRANCH == emptyBigDecimalValue" >
            FACILITY_BRANCH = NULL ,
          </when>
          <otherwise >
            FACILITY_BRANCH = #{FACILITY_BRANCH},
          </otherwise>
        </choose>
      </if>
      <if test="FACILITY_NO != null" >
        <choose >
          <when test="FACILITY_NO == emptyBigDecimalValue" >
            FACILITY_NO = NULL ,
          </when>
          <otherwise >
            FACILITY_NO = #{FACILITY_NO},
          </otherwise>
        </choose>
      </if>
      <if test="SUBLIMIT_NO != null" >
        <choose >
          <when test="SUBLIMIT_NO == emptyBigDecimalValue" >
            SUBLIMIT_NO = NULL ,
          </when>
          <otherwise >
            SUBLIMIT_NO = #{SUBLIMIT_NO},
          </otherwise>
        </choose>
      </if>
      <if test="TAX_ANNUAL_DEPRECIATION_RATE != null" >
        <choose >
          <when test="TAX_ANNUAL_DEPRECIATION_RATE == emptyBigDecimalValue" >
            TAX_ANNUAL_DEPRECIATION_RATE = NULL ,
          </when>
          <otherwise >
            TAX_ANNUAL_DEPRECIATION_RATE = #{TAX_ANNUAL_DEPRECIATION_RATE},
          </otherwise>
        </choose>
      </if>
      <if test="TAX_DEFAULT_USEFUL_LIFE != null" >
        <choose >
          <when test="TAX_DEFAULT_USEFUL_LIFE == emptyBigDecimalValue" >
            TAX_DEFAULT_USEFUL_LIFE = NULL ,
          </when>
          <otherwise >
            TAX_DEFAULT_USEFUL_LIFE = #{TAX_DEFAULT_USEFUL_LIFE},
          </otherwise>
        </choose>
      </if>
      <if test="TAX_DEPRECIATION_BASIS != null" >
        <choose >
          <when test="TAX_DEPRECIATION_BASIS == emptyBigDecimalValue" >
            TAX_DEPRECIATION_BASIS = NULL ,
          </when>
          <otherwise >
            TAX_DEPRECIATION_BASIS = #{TAX_DEPRECIATION_BASIS},
          </otherwise>
        </choose>
      </if>
      <if test="TAX_DEPRECIATION_METHOD != null" >
        <choose >
          <when test="TAX_DEPRECIATION_METHOD == emptyBigDecimalValue" >
            TAX_DEPRECIATION_METHOD = NULL ,
          </when>
          <otherwise >
            TAX_DEPRECIATION_METHOD = #{TAX_DEPRECIATION_METHOD},
          </otherwise>
        </choose>
      </if>
      <if test="TAX_INIT_ALLOWANCE_PERC != null" >
        <choose >
          <when test="TAX_INIT_ALLOWANCE_PERC == emptyBigDecimalValue" >
            TAX_INIT_ALLOWANCE_PERC = NULL ,
          </when>
          <otherwise >
            TAX_INIT_ALLOWANCE_PERC = #{TAX_INIT_ALLOWANCE_PERC},
          </otherwise>
        </choose>
      </if>
      <if test="LAST_TAX_DEPRECIATION_DATE != null" >
        LAST_TAX_DEPRECIATION_DATE = #{LAST_TAX_DEPRECIATION_DATE},
      </if>
      <if test="TAX_ACCUMU_DEPRECIATION_VALUE != null" >
        <choose >
          <when test="TAX_ACCUMU_DEPRECIATION_VALUE == emptyBigDecimalValue" >
            TAX_ACCUMU_DEPRECIATION_VALUE = NULL ,
          </when>
          <otherwise >
            TAX_ACCUMU_DEPRECIATION_VALUE = #{TAX_ACCUMU_DEPRECIATION_VALUE},
          </otherwise>
        </choose>
      </if>
      <if test="TAX_DEPRECIATION_RATE != null" >
        <choose >
          <when test="TAX_DEPRECIATION_RATE == emptyBigDecimalValue" >
            TAX_DEPRECIATION_RATE = NULL ,
          </when>
          <otherwise >
            TAX_DEPRECIATION_RATE = #{TAX_DEPRECIATION_RATE},
          </otherwise>
        </choose>
      </if>
      <if test="TAX_REMAINING_LIFE != null" >
        <choose >
          <when test="TAX_REMAINING_LIFE == emptyBigDecimalValue" >
            TAX_REMAINING_LIFE = NULL ,
          </when>
          <otherwise >
            TAX_REMAINING_LIFE = #{TAX_REMAINING_LIFE},
          </otherwise>
        </choose>
      </if>
      <if test="TAX_USEFUL_LIFE != null" >
        <choose >
          <when test="TAX_USEFUL_LIFE == emptyBigDecimalValue" >
            TAX_USEFUL_LIFE = NULL ,
          </when>
          <otherwise >
            TAX_USEFUL_LIFE = #{TAX_USEFUL_LIFE},
          </otherwise>
        </choose>
      </if>
      <if test="TAX_UTILIZED_PERIOD != null" >
        <choose >
          <when test="TAX_UTILIZED_PERIOD == emptyBigDecimalValue" >
            TAX_UTILIZED_PERIOD = NULL ,
          </when>
          <otherwise >
            TAX_UTILIZED_PERIOD = #{TAX_UTILIZED_PERIOD},
          </otherwise>
        </choose>
      </if>
      <if test="ASSET_CY_CODE != null" >
        <choose >
          <when test="ASSET_CY_CODE == emptyBigDecimalValue" >
            ASSET_CY_CODE = NULL ,
          </when>
          <otherwise >
            ASSET_CY_CODE = #{ASSET_CY_CODE},
          </otherwise>
        </choose>
      </if>
      <if test="APPROVED_BY != null" >
        <choose >
          <when test="APPROVED_BY.equals(&quot;&quot;)" >
            APPROVED_BY = NULL ,
          </when>
          <otherwise >
            APPROVED_BY = #{APPROVED_BY},
          </otherwise>
        </choose>
      </if>
      <if test="DATE_APPROVED != null" >
        DATE_APPROVED = #{DATE_APPROVED},
      </if>
      <if test="DATE_MODIFIED != null" >
        DATE_MODIFIED = #{DATE_MODIFIED},
      </if>
      <if test="MODIFIED_BY != null" >
        <choose >
          <when test="MODIFIED_BY.equals(&quot;&quot;)" >
            MODIFIED_BY = NULL ,
          </when>
          <otherwise >
            MODIFIED_BY = #{MODIFIED_BY},
          </otherwise>
        </choose>
      </if>
      <if test="SERVER_APPROVED_DATE != null" >
        SERVER_APPROVED_DATE = #{SERVER_APPROVED_DATE},
      </if>
      <if test="SERVER_MODIFIED_DATE != null" >
        SERVER_MODIFIED_DATE = #{SERVER_MODIFIED_DATE},
      </if>
      <if test="FACILITY_ASSET_LINE_NO != null" >
        <choose >
          <when test="FACILITY_ASSET_LINE_NO == emptyBigDecimalValue" >
            FACILITY_ASSET_LINE_NO = NULL ,
          </when>
          <otherwise >
            FACILITY_ASSET_LINE_NO = #{FACILITY_ASSET_LINE_NO},
          </otherwise>
        </choose>
      </if>
      DATE_UPDATED = 
      <choose >
        <when test="isSybase == 1" >
           GETDATE(),
        </when>
        <otherwise >
           SYSDATE,
        </otherwise>
      </choose>
      <if test="VENDOR_DOWN_PAYMENT != null" >
        <choose >
          <when test="VENDOR_DOWN_PAYMENT == emptyBigDecimalValue" >
            VENDOR_DOWN_PAYMENT = NULL ,
          </when>
          <otherwise >
            VENDOR_DOWN_PAYMENT = #{VENDOR_DOWN_PAYMENT},
          </otherwise>
        </choose>
      </if>
      <if test="SUB_STATUS != null" >
        <choose >
          <when test="SUB_STATUS == emptyBigDecimalValue" >
            SUB_STATUS = NULL ,
          </when>
          <otherwise >
            SUB_STATUS = #{SUB_STATUS},
          </otherwise>
        </choose>
      </if>
      <if test="ASSET_SUB_STATUS != null" >
        <choose >
          <when test="ASSET_SUB_STATUS == emptyBigDecimalValue" >
            ASSET_SUB_STATUS = NULL ,
          </when>
          <otherwise >
            ASSET_SUB_STATUS = #{ASSET_SUB_STATUS},
          </otherwise>
        </choose>
      </if>
      <if test="DOWN_PAYMENT_AMOUNT != null" >
        <choose >
          <when test="DOWN_PAYMENT_AMOUNT == emptyBigDecimalValue" >
            DOWN_PAYMENT_AMOUNT = NULL ,
          </when>
          <otherwise >
            DOWN_PAYMENT_AMOUNT = #{DOWN_PAYMENT_AMOUNT},
          </otherwise>
        </choose>
      </if>
    </set>
    where CATEGORY_CODE = #{CATEGORY_CODE}
      and CLASS_CODE = #{CLASS_CODE}
      and CODE = #{CODE}
      and COMP_CODE = #{COMP_CODE}
  </sql>
  <update id="updateFASAST" parameterType="com.path.dbmaps.vo.FASASTVO" >
    <include refid="sql_updateFASAST" />
    <if test="DATE_UPDATED != null" >
      AND DATE_UPDATED = #{DATE_UPDATED}
    </if>
  </update>
</mapper>